[
{
    "model": "insp.wppostmeta",
    "pk": 4,
    "fields": {
        "post_id": 6,
        "meta_key": "_wp_attached_file",
        "meta_value": "2012/10/bg.jpg"
    }
},
{
    "model": "insp.wppostmeta",
    "pk": 5,
    "fields": {
        "post_id": 6,
        "meta_key": "_wp_attachment_metadata",
        "meta_value": "a:5:{s:5:\"width\";i:1920;s:6:\"height\";i:1080;s:4:\"file\";s:14:\"2012/10/bg.jpg\";s:5:\"sizes\";a:4:{s:9:\"thumbnail\";a:4:{s:4:\"file\";s:14:\"bg-150x150.jpg\";s:5:\"width\";i:150;s:6:\"height\";i:150;s:9:\"mime-type\";s:10:\"image/jpeg\";}s:6:\"medium\";a:4:{s:4:\"file\";s:14:\"bg-300x168.jpg\";s:5:\"width\";i:300;s:6:\"height\";i:168;s:9:\"mime-type\";s:10:\"image/jpeg\";}s:5:\"large\";a:4:{s:4:\"file\";s:15:\"bg-1024x576.jpg\";s:5:\"width\";i:1024;s:6:\"height\";i:576;s:9:\"mime-type\";s:10:\"image/jpeg\";}s:14:\"post-thumbnail\";a:4:{s:4:\"file\";s:14:\"bg-604x270.jpg\";s:5:\"width\";i:604;s:6:\"height\";i:270;s:9:\"mime-type\";s:10:\"image/jpeg\";}}s:10:\"image_meta\";a:10:{s:8:\"aperture\";i:0;s:6:\"credit\";s:0:\"\";s:6:\"camera\";s:0:\"\";s:7:\"caption\";s:0:\"\";s:17:\"created_timestamp\";i:0;s:9:\"copyright\";s:0:\"\";s:12:\"focal_length\";i:0;s:3:\"iso\";i:0;s:13:\"shutter_speed\";i:0;s:5:\"title\";s:0:\"\";}}"
    }
},
{
    "model": "insp.wppostmeta",
    "pk": 6,
    "fields": {
        "post_id": 23,
        "meta_key": "_wp_attached_file",
        "meta_value": "2012/11/2012-11-05-23.05.56.jpg"
    }
},
{
    "model": "insp.wppostmeta",
    "pk": 7,
    "fields": {
        "post_id": 23,
        "meta_key": "_wp_attachment_metadata",
        "meta_value": "a:5:{s:5:\"width\";i:2592;s:6:\"height\";i:1944;s:4:\"file\";s:31:\"2012/11/2012-11-05-23.05.56.jpg\";s:5:\"sizes\";a:4:{s:9:\"thumbnail\";a:4:{s:4:\"file\";s:31:\"2012-11-05-23.05.56-150x150.jpg\";s:5:\"width\";i:150;s:6:\"height\";i:150;s:9:\"mime-type\";s:10:\"image/jpeg\";}s:6:\"medium\";a:4:{s:4:\"file\";s:31:\"2012-11-05-23.05.56-300x225.jpg\";s:5:\"width\";i:300;s:6:\"height\";i:225;s:9:\"mime-type\";s:10:\"image/jpeg\";}s:5:\"large\";a:4:{s:4:\"file\";s:32:\"2012-11-05-23.05.56-1024x768.jpg\";s:5:\"width\";i:1024;s:6:\"height\";i:768;s:9:\"mime-type\";s:10:\"image/jpeg\";}s:14:\"post-thumbnail\";a:4:{s:4:\"file\";s:31:\"2012-11-05-23.05.56-604x270.jpg\";s:5:\"width\";i:604;s:6:\"height\";i:270;s:9:\"mime-type\";s:10:\"image/jpeg\";}}s:10:\"image_meta\";a:10:{s:8:\"aperture\";i:0;s:6:\"credit\";s:0:\"\";s:6:\"camera\";s:4:\"E10i\";s:7:\"caption\";s:0:\"\";s:17:\"created_timestamp\";i:1352156756;s:9:\"copyright\";s:0:\"\";s:12:\"focal_length\";i:0;s:3:\"iso\";s:2:\"80\";s:13:\"shutter_speed\";s:17:\"0.033333333333333\";s:5:\"title\";s:0:\"\";}}"
    }
},
{
    "model": "insp.wppostmeta",
    "pk": 8,
    "fields": {
        "post_id": 24,
        "meta_key": "_wp_attached_file",
        "meta_value": "2012/11/2012-11-05-23.06.28.jpg"
    }
},
{
    "model": "insp.wppostmeta",
    "pk": 9,
    "fields": {
        "post_id": 24,
        "meta_key": "_wp_attachment_metadata",
        "meta_value": "a:5:{s:5:\"width\";i:2592;s:6:\"height\";i:1944;s:4:\"file\";s:31:\"2012/11/2012-11-05-23.06.28.jpg\";s:5:\"sizes\";a:4:{s:9:\"thumbnail\";a:4:{s:4:\"file\";s:31:\"2012-11-05-23.06.28-150x150.jpg\";s:5:\"width\";i:150;s:6:\"height\";i:150;s:9:\"mime-type\";s:10:\"image/jpeg\";}s:6:\"medium\";a:4:{s:4:\"file\";s:31:\"2012-11-05-23.06.28-300x225.jpg\";s:5:\"width\";i:300;s:6:\"height\";i:225;s:9:\"mime-type\";s:10:\"image/jpeg\";}s:5:\"large\";a:4:{s:4:\"file\";s:32:\"2012-11-05-23.06.28-1024x768.jpg\";s:5:\"width\";i:1024;s:6:\"height\";i:768;s:9:\"mime-type\";s:10:\"image/jpeg\";}s:14:\"post-thumbnail\";a:4:{s:4:\"file\";s:31:\"2012-11-05-23.06.28-604x270.jpg\";s:5:\"width\";i:604;s:6:\"height\";i:270;s:9:\"mime-type\";s:10:\"image/jpeg\";}}s:10:\"image_meta\";a:10:{s:8:\"aperture\";i:0;s:6:\"credit\";s:0:\"\";s:6:\"camera\";s:4:\"E10i\";s:7:\"caption\";s:0:\"\";s:17:\"created_timestamp\";i:1352156788;s:9:\"copyright\";s:0:\"\";s:12:\"focal_length\";i:0;s:3:\"iso\";s:2:\"80\";s:13:\"shutter_speed\";s:17:\"0.033333333333333\";s:5:\"title\";s:0:\"\";}}"
    }
},
{
    "model": "insp.wppostmeta",
    "pk": 10,
    "fields": {
        "post_id": 38,
        "meta_key": "_wp_attached_file",
        "meta_value": "2012/11/035-A-gift-from-Jesus1.jpg"
    }
},
{
    "model": "insp.wppostmeta",
    "pk": 11,
    "fields": {
        "post_id": 38,
        "meta_key": "_wp_attachment_metadata",
        "meta_value": "a:5:{s:5:\"width\";i:500;s:6:\"height\";i:465;s:4:\"file\";s:34:\"2012/11/035-A-gift-from-Jesus1.jpg\";s:5:\"sizes\";a:3:{s:9:\"thumbnail\";a:4:{s:4:\"file\";s:34:\"035-A-gift-from-Jesus1-150x150.jpg\";s:5:\"width\";i:150;s:6:\"height\";i:150;s:9:\"mime-type\";s:10:\"image/jpeg\";}s:6:\"medium\";a:4:{s:4:\"file\";s:34:\"035-A-gift-from-Jesus1-300x279.jpg\";s:5:\"width\";i:300;s:6:\"height\";i:279;s:9:\"mime-type\";s:10:\"image/jpeg\";}s:14:\"post-thumbnail\";a:4:{s:4:\"file\";s:34:\"035-A-gift-from-Jesus1-500x270.jpg\";s:5:\"width\";i:500;s:6:\"height\";i:270;s:9:\"mime-type\";s:10:\"image/jpeg\";}}s:10:\"image_meta\";a:10:{s:8:\"aperture\";i:0;s:6:\"credit\";s:0:\"\";s:6:\"camera\";s:0:\"\";s:7:\"caption\";s:0:\"\";s:17:\"created_timestamp\";i:0;s:9:\"copyright\";s:0:\"\";s:12:\"focal_length\";i:0;s:3:\"iso\";i:0;s:13:\"shutter_speed\";i:0;s:5:\"title\";s:0:\"\";}}"
    }
},
{
    "model": "insp.wppostmeta",
    "pk": 12,
    "fields": {
        "post_id": 43,
        "meta_key": "_wp_attached_file",
        "meta_value": "2012/11/MNoop.jpg"
    }
},
{
    "model": "insp.wppostmeta",
    "pk": 13,
    "fields": {
        "post_id": 43,
        "meta_key": "_wp_attachment_metadata",
        "meta_value": "a:5:{s:5:\"width\";i:615;s:6:\"height\";i:10079;s:4:\"file\";s:17:\"2012/11/MNoop.jpg\";s:5:\"sizes\";a:4:{s:9:\"thumbnail\";a:4:{s:4:\"file\";s:17:\"MNoop-150x150.jpg\";s:5:\"width\";i:150;s:6:\"height\";i:150;s:9:\"mime-type\";s:10:\"image/jpeg\";}s:6:\"medium\";a:4:{s:4:\"file\";s:16:\"MNoop-18x300.jpg\";s:5:\"width\";i:18;s:6:\"height\";i:300;s:9:\"mime-type\";s:10:\"image/jpeg\";}s:5:\"large\";a:4:{s:4:\"file\";s:17:\"MNoop-62x1024.jpg\";s:5:\"width\";i:62;s:6:\"height\";i:1024;s:9:\"mime-type\";s:10:\"image/jpeg\";}s:14:\"post-thumbnail\";a:4:{s:4:\"file\";s:17:\"MNoop-604x270.jpg\";s:5:\"width\";i:604;s:6:\"height\";i:270;s:9:\"mime-type\";s:10:\"image/jpeg\";}}s:10:\"image_meta\";a:10:{s:8:\"aperture\";i:0;s:6:\"credit\";s:0:\"\";s:6:\"camera\";s:0:\"\";s:7:\"caption\";s:0:\"\";s:17:\"created_timestamp\";i:0;s:9:\"copyright\";s:0:\"\";s:12:\"focal_length\";i:0;s:3:\"iso\";i:0;s:13:\"shutter_speed\";i:0;s:5:\"title\";s:0:\"\";}}"
    }
},
{
    "model": "insp.wppostmeta",
    "pk": 14,
    "fields": {
        "post_id": 48,
        "meta_key": "_wp_attached_file",
        "meta_value": "2012/11/tsipouro_me_meze.jpg"
    }
},
{
    "model": "insp.wppostmeta",
    "pk": 15,
    "fields": {
        "post_id": 48,
        "meta_key": "_wp_attachment_metadata",
        "meta_value": "a:5:{s:5:\"width\";i:480;s:6:\"height\";i:309;s:4:\"file\";s:28:\"2012/11/tsipouro_me_meze.jpg\";s:5:\"sizes\";a:3:{s:9:\"thumbnail\";a:4:{s:4:\"file\";s:28:\"tsipouro_me_meze-150x150.jpg\";s:5:\"width\";i:150;s:6:\"height\";i:150;s:9:\"mime-type\";s:10:\"image/jpeg\";}s:6:\"medium\";a:4:{s:4:\"file\";s:28:\"tsipouro_me_meze-300x193.jpg\";s:5:\"width\";i:300;s:6:\"height\";i:193;s:9:\"mime-type\";s:10:\"image/jpeg\";}s:14:\"post-thumbnail\";a:4:{s:4:\"file\";s:28:\"tsipouro_me_meze-480x270.jpg\";s:5:\"width\";i:480;s:6:\"height\";i:270;s:9:\"mime-type\";s:10:\"image/jpeg\";}}s:10:\"image_meta\";a:10:{s:8:\"aperture\";i:0;s:6:\"credit\";s:0:\"\";s:6:\"camera\";s:0:\"\";s:7:\"caption\";s:0:\"\";s:17:\"created_timestamp\";i:0;s:9:\"copyright\";s:0:\"\";s:12:\"focal_length\";i:0;s:3:\"iso\";i:0;s:13:\"shutter_speed\";i:0;s:5:\"title\";s:0:\"\";}}"
    }
},
{
    "model": "insp.wppostmeta",
    "pk": 16,
    "fields": {
        "post_id": 52,
        "meta_key": "_wp_attached_file",
        "meta_value": "2012/11/Screen-Shot-2012-11-17-at-8.52.37-PM.png"
    }
},
{
    "model": "insp.wppostmeta",
    "pk": 17,
    "fields": {
        "post_id": 52,
        "meta_key": "_wp_attachment_metadata",
        "meta_value": "a:5:{s:5:\"width\";i:931;s:6:\"height\";i:365;s:4:\"file\";s:48:\"2012/11/Screen-Shot-2012-11-17-at-8.52.37-PM.png\";s:5:\"sizes\";a:3:{s:9:\"thumbnail\";a:4:{s:4:\"file\";s:48:\"Screen-Shot-2012-11-17-at-8.52.37-PM-150x150.png\";s:5:\"width\";i:150;s:6:\"height\";i:150;s:9:\"mime-type\";s:9:\"image/png\";}s:6:\"medium\";a:4:{s:4:\"file\";s:48:\"Screen-Shot-2012-11-17-at-8.52.37-PM-300x117.png\";s:5:\"width\";i:300;s:6:\"height\";i:117;s:9:\"mime-type\";s:9:\"image/png\";}s:14:\"post-thumbnail\";a:4:{s:4:\"file\";s:48:\"Screen-Shot-2012-11-17-at-8.52.37-PM-604x270.png\";s:5:\"width\";i:604;s:6:\"height\";i:270;s:9:\"mime-type\";s:9:\"image/png\";}}s:10:\"image_meta\";a:10:{s:8:\"aperture\";i:0;s:6:\"credit\";s:0:\"\";s:6:\"camera\";s:0:\"\";s:7:\"caption\";s:0:\"\";s:17:\"created_timestamp\";i:0;s:9:\"copyright\";s:0:\"\";s:12:\"focal_length\";i:0;s:3:\"iso\";i:0;s:13:\"shutter_speed\";i:0;s:5:\"title\";s:0:\"\";}}"
    }
},
{
    "model": "insp.wppostmeta",
    "pk": 18,
    "fields": {
        "post_id": 56,
        "meta_key": "_wp_attached_file",
        "meta_value": "2012/11/IMG_20121121_142653.jpg"
    }
},
{
    "model": "insp.wppostmeta",
    "pk": 19,
    "fields": {
        "post_id": 56,
        "meta_key": "_wp_attachment_metadata",
        "meta_value": "a:5:{s:5:\"width\";i:2592;s:6:\"height\";i:1944;s:4:\"file\";s:31:\"2012/11/IMG_20121121_142653.jpg\";s:5:\"sizes\";a:4:{s:9:\"thumbnail\";a:4:{s:4:\"file\";s:31:\"IMG_20121121_142653-150x150.jpg\";s:5:\"width\";i:150;s:6:\"height\";i:150;s:9:\"mime-type\";s:10:\"image/jpeg\";}s:6:\"medium\";a:4:{s:4:\"file\";s:31:\"IMG_20121121_142653-300x225.jpg\";s:5:\"width\";i:300;s:6:\"height\";i:225;s:9:\"mime-type\";s:10:\"image/jpeg\";}s:5:\"large\";a:4:{s:4:\"file\";s:32:\"IMG_20121121_142653-1024x768.jpg\";s:5:\"width\";i:1024;s:6:\"height\";i:768;s:9:\"mime-type\";s:10:\"image/jpeg\";}s:14:\"post-thumbnail\";a:4:{s:4:\"file\";s:31:\"IMG_20121121_142653-604x270.jpg\";s:5:\"width\";i:604;s:6:\"height\";i:270;s:9:\"mime-type\";s:10:\"image/jpeg\";}}s:10:\"image_meta\";a:10:{s:8:\"aperture\";i:0;s:6:\"credit\";s:0:\"\";s:6:\"camera\";s:4:\"E10i\";s:7:\"caption\";s:0:\"\";s:17:\"created_timestamp\";i:1353508013;s:9:\"copyright\";s:0:\"\";s:12:\"focal_length\";i:0;s:3:\"iso\";s:3:\"160\";s:13:\"shutter_speed\";s:3:\"0.1\";s:5:\"title\";s:0:\"\";}}"
    }
},
{
    "model": "insp.wppostmeta",
    "pk": 20,
    "fields": {
        "post_id": 57,
        "meta_key": "_wp_attached_file",
        "meta_value": "2012/11/IMG_20121121_144329.jpg"
    }
},
{
    "model": "insp.wppostmeta",
    "pk": 21,
    "fields": {
        "post_id": 57,
        "meta_key": "_wp_attachment_metadata",
        "meta_value": "a:5:{s:5:\"width\";i:2592;s:6:\"height\";i:1944;s:4:\"file\";s:31:\"2012/11/IMG_20121121_144329.jpg\";s:5:\"sizes\";a:4:{s:9:\"thumbnail\";a:4:{s:4:\"file\";s:31:\"IMG_20121121_144329-150x150.jpg\";s:5:\"width\";i:150;s:6:\"height\";i:150;s:9:\"mime-type\";s:10:\"image/jpeg\";}s:6:\"medium\";a:4:{s:4:\"file\";s:31:\"IMG_20121121_144329-300x225.jpg\";s:5:\"width\";i:300;s:6:\"height\";i:225;s:9:\"mime-type\";s:10:\"image/jpeg\";}s:5:\"large\";a:4:{s:4:\"file\";s:32:\"IMG_20121121_144329-1024x768.jpg\";s:5:\"width\";i:1024;s:6:\"height\";i:768;s:9:\"mime-type\";s:10:\"image/jpeg\";}s:14:\"post-thumbnail\";a:4:{s:4:\"file\";s:31:\"IMG_20121121_144329-604x270.jpg\";s:5:\"width\";i:604;s:6:\"height\";i:270;s:9:\"mime-type\";s:10:\"image/jpeg\";}}s:10:\"image_meta\";a:10:{s:8:\"aperture\";i:0;s:6:\"credit\";s:0:\"\";s:6:\"camera\";s:4:\"E10i\";s:7:\"caption\";s:0:\"\";s:17:\"created_timestamp\";i:1353509009;s:9:\"copyright\";s:0:\"\";s:12:\"focal_length\";i:0;s:3:\"iso\";s:2:\"40\";s:13:\"shutter_speed\";s:6:\"0.0125\";s:5:\"title\";s:0:\"\";}}"
    }
},
{
    "model": "insp.wppostmeta",
    "pk": 22,
    "fields": {
        "post_id": 65,
        "meta_key": "_wp_attached_file",
        "meta_value": "2012/11/IMG_20121120_203639.jpg"
    }
},
{
    "model": "insp.wppostmeta",
    "pk": 23,
    "fields": {
        "post_id": 65,
        "meta_key": "_wp_attachment_metadata",
        "meta_value": "a:5:{s:5:\"width\";i:2592;s:6:\"height\";i:1944;s:4:\"file\";s:31:\"2012/11/IMG_20121120_203639.jpg\";s:5:\"sizes\";a:4:{s:9:\"thumbnail\";a:4:{s:4:\"file\";s:31:\"IMG_20121120_203639-150x150.jpg\";s:5:\"width\";i:150;s:6:\"height\";i:150;s:9:\"mime-type\";s:10:\"image/jpeg\";}s:6:\"medium\";a:4:{s:4:\"file\";s:31:\"IMG_20121120_203639-300x225.jpg\";s:5:\"width\";i:300;s:6:\"height\";i:225;s:9:\"mime-type\";s:10:\"image/jpeg\";}s:5:\"large\";a:4:{s:4:\"file\";s:32:\"IMG_20121120_203639-1024x768.jpg\";s:5:\"width\";i:1024;s:6:\"height\";i:768;s:9:\"mime-type\";s:10:\"image/jpeg\";}s:14:\"post-thumbnail\";a:4:{s:4:\"file\";s:31:\"IMG_20121120_203639-604x270.jpg\";s:5:\"width\";i:604;s:6:\"height\";i:270;s:9:\"mime-type\";s:10:\"image/jpeg\";}}s:10:\"image_meta\";a:10:{s:8:\"aperture\";i:0;s:6:\"credit\";s:0:\"\";s:6:\"camera\";s:4:\"E10i\";s:7:\"caption\";s:0:\"\";s:17:\"created_timestamp\";i:1353443799;s:9:\"copyright\";s:0:\"\";s:12:\"focal_length\";i:0;s:3:\"iso\";s:3:\"250\";s:13:\"shutter_speed\";s:5:\"0.125\";s:5:\"title\";s:0:\"\";}}"
    }
},
{
    "model": "insp.wppostmeta",
    "pk": 24,
    "fields": {
        "post_id": 70,
        "meta_key": "_wp_attached_file",
        "meta_value": "2012/11/Screenshot-112612-1159-PM-2.jpeg"
    }
},
{
    "model": "insp.wppostmeta",
    "pk": 25,
    "fields": {
        "post_id": 70,
        "meta_key": "_wp_attachment_metadata",
        "meta_value": "a:5:{s:5:\"width\";i:464;s:6:\"height\";i:234;s:4:\"file\";s:40:\"2012/11/Screenshot-112612-1159-PM-2.jpeg\";s:5:\"sizes\";a:2:{s:9:\"thumbnail\";a:4:{s:4:\"file\";s:40:\"Screenshot-112612-1159-PM-2-150x150.jpeg\";s:5:\"width\";i:150;s:6:\"height\";i:150;s:9:\"mime-type\";s:10:\"image/jpeg\";}s:6:\"medium\";a:4:{s:4:\"file\";s:40:\"Screenshot-112612-1159-PM-2-300x151.jpeg\";s:5:\"width\";i:300;s:6:\"height\";i:151;s:9:\"mime-type\";s:10:\"image/jpeg\";}}s:10:\"image_meta\";a:10:{s:8:\"aperture\";i:0;s:6:\"credit\";s:0:\"\";s:6:\"camera\";s:0:\"\";s:7:\"caption\";s:0:\"\";s:17:\"created_timestamp\";i:0;s:9:\"copyright\";s:0:\"\";s:12:\"focal_length\";i:0;s:3:\"iso\";i:0;s:13:\"shutter_speed\";i:0;s:5:\"title\";s:0:\"\";}}"
    }
},
{
    "model": "insp.wppostmeta",
    "pk": 26,
    "fields": {
        "post_id": 80,
        "meta_key": "_wp_attached_file",
        "meta_value": "2012/12/matsakoniazw.jpeg"
    }
},
{
    "model": "insp.wppostmeta",
    "pk": 27,
    "fields": {
        "post_id": 80,
        "meta_key": "_wp_attachment_metadata",
        "meta_value": "a:5:{s:5:\"width\";i:587;s:6:\"height\";i:296;s:4:\"file\";s:25:\"2012/12/matsakoniazw.jpeg\";s:5:\"sizes\";a:3:{s:9:\"thumbnail\";a:4:{s:4:\"file\";s:25:\"matsakoniazw-150x150.jpeg\";s:5:\"width\";i:150;s:6:\"height\";i:150;s:9:\"mime-type\";s:10:\"image/jpeg\";}s:6:\"medium\";a:4:{s:4:\"file\";s:25:\"matsakoniazw-300x151.jpeg\";s:5:\"width\";i:300;s:6:\"height\";i:151;s:9:\"mime-type\";s:10:\"image/jpeg\";}s:14:\"post-thumbnail\";a:4:{s:4:\"file\";s:25:\"matsakoniazw-587x270.jpeg\";s:5:\"width\";i:587;s:6:\"height\";i:270;s:9:\"mime-type\";s:10:\"image/jpeg\";}}s:10:\"image_meta\";a:10:{s:8:\"aperture\";i:0;s:6:\"credit\";s:0:\"\";s:6:\"camera\";s:0:\"\";s:7:\"caption\";s:0:\"\";s:17:\"created_timestamp\";i:0;s:9:\"copyright\";s:0:\"\";s:12:\"focal_length\";i:0;s:3:\"iso\";i:0;s:13:\"shutter_speed\";i:0;s:5:\"title\";s:0:\"\";}}"
    }
},
{
    "model": "insp.wppostmeta",
    "pk": 28,
    "fields": {
        "post_id": 100,
        "meta_key": "_wp_attached_file",
        "meta_value": "2012/12/Screenshot-12812-537-AM.jpeg"
    }
},
{
    "model": "insp.wppostmeta",
    "pk": 29,
    "fields": {
        "post_id": 100,
        "meta_key": "_wp_attachment_metadata",
        "meta_value": "a:5:{s:5:\"width\";i:353;s:6:\"height\";i:172;s:4:\"file\";s:36:\"2012/12/Screenshot-12812-537-AM.jpeg\";s:5:\"sizes\";a:2:{s:9:\"thumbnail\";a:4:{s:4:\"file\";s:36:\"Screenshot-12812-537-AM-150x150.jpeg\";s:5:\"width\";i:150;s:6:\"height\";i:150;s:9:\"mime-type\";s:10:\"image/jpeg\";}s:6:\"medium\";a:4:{s:4:\"file\";s:36:\"Screenshot-12812-537-AM-300x146.jpeg\";s:5:\"width\";i:300;s:6:\"height\";i:146;s:9:\"mime-type\";s:10:\"image/jpeg\";}}s:10:\"image_meta\";a:10:{s:8:\"aperture\";i:0;s:6:\"credit\";s:0:\"\";s:6:\"camera\";s:0:\"\";s:7:\"caption\";s:0:\"\";s:17:\"created_timestamp\";i:0;s:9:\"copyright\";s:0:\"\";s:12:\"focal_length\";i:0;s:3:\"iso\";i:0;s:13:\"shutter_speed\";i:0;s:5:\"title\";s:0:\"\";}}"
    }
},
{
    "model": "insp.wppostmeta",
    "pk": 30,
    "fields": {
        "post_id": 105,
        "meta_key": "_wp_attached_file",
        "meta_value": "2012/12/Screenshot-121012-403-PM.jpeg"
    }
},
{
    "model": "insp.wppostmeta",
    "pk": 31,
    "fields": {
        "post_id": 105,
        "meta_key": "_wp_attachment_metadata",
        "meta_value": "a:5:{s:5:\"width\";i:650;s:6:\"height\";i:442;s:4:\"file\";s:37:\"2012/12/Screenshot-121012-403-PM.jpeg\";s:5:\"sizes\";a:3:{s:9:\"thumbnail\";a:4:{s:4:\"file\";s:37:\"Screenshot-121012-403-PM-150x150.jpeg\";s:5:\"width\";i:150;s:6:\"height\";i:150;s:9:\"mime-type\";s:10:\"image/jpeg\";}s:6:\"medium\";a:4:{s:4:\"file\";s:37:\"Screenshot-121012-403-PM-300x204.jpeg\";s:5:\"width\";i:300;s:6:\"height\";i:204;s:9:\"mime-type\";s:10:\"image/jpeg\";}s:14:\"post-thumbnail\";a:4:{s:4:\"file\";s:37:\"Screenshot-121012-403-PM-604x270.jpeg\";s:5:\"width\";i:604;s:6:\"height\";i:270;s:9:\"mime-type\";s:10:\"image/jpeg\";}}s:10:\"image_meta\";a:10:{s:8:\"aperture\";i:0;s:6:\"credit\";s:0:\"\";s:6:\"camera\";s:0:\"\";s:7:\"caption\";s:0:\"\";s:17:\"created_timestamp\";i:0;s:9:\"copyright\";s:0:\"\";s:12:\"focal_length\";i:0;s:3:\"iso\";i:0;s:13:\"shutter_speed\";i:0;s:5:\"title\";s:0:\"\";}}"
    }
},
{
    "model": "insp.wppostmeta",
    "pk": 32,
    "fields": {
        "post_id": 115,
        "meta_key": "_wp_attached_file",
        "meta_value": "2012/12/photo.png"
    }
},
{
    "model": "insp.wppostmeta",
    "pk": 33,
    "fields": {
        "post_id": 115,
        "meta_key": "_wp_attachment_metadata",
        "meta_value": "a:5:{s:5:\"width\";i:640;s:6:\"height\";i:960;s:4:\"file\";s:17:\"2012/12/photo.png\";s:5:\"sizes\";a:3:{s:9:\"thumbnail\";a:4:{s:4:\"file\";s:17:\"photo-150x150.png\";s:5:\"width\";i:150;s:6:\"height\";i:150;s:9:\"mime-type\";s:9:\"image/png\";}s:6:\"medium\";a:4:{s:4:\"file\";s:17:\"photo-200x300.png\";s:5:\"width\";i:200;s:6:\"height\";i:300;s:9:\"mime-type\";s:9:\"image/png\";}s:14:\"post-thumbnail\";a:4:{s:4:\"file\";s:17:\"photo-604x270.png\";s:5:\"width\";i:604;s:6:\"height\";i:270;s:9:\"mime-type\";s:9:\"image/png\";}}s:10:\"image_meta\";a:10:{s:8:\"aperture\";i:0;s:6:\"credit\";s:0:\"\";s:6:\"camera\";s:0:\"\";s:7:\"caption\";s:0:\"\";s:17:\"created_timestamp\";i:0;s:9:\"copyright\";s:0:\"\";s:12:\"focal_length\";i:0;s:3:\"iso\";i:0;s:13:\"shutter_speed\";i:0;s:5:\"title\";s:0:\"\";}}"
    }
},
{
    "model": "insp.wppostmeta",
    "pk": 34,
    "fields": {
        "post_id": 123,
        "meta_key": "_wp_attached_file",
        "meta_value": "2012/12/Screenshot-123012-741-PM.jpeg"
    }
},
{
    "model": "insp.wppostmeta",
    "pk": 35,
    "fields": {
        "post_id": 123,
        "meta_key": "_wp_attachment_metadata",
        "meta_value": "a:5:{s:5:\"width\";i:919;s:6:\"height\";i:680;s:4:\"file\";s:37:\"2012/12/Screenshot-123012-741-PM.jpeg\";s:5:\"sizes\";a:3:{s:9:\"thumbnail\";a:4:{s:4:\"file\";s:37:\"Screenshot-123012-741-PM-150x150.jpeg\";s:5:\"width\";i:150;s:6:\"height\";i:150;s:9:\"mime-type\";s:10:\"image/jpeg\";}s:6:\"medium\";a:4:{s:4:\"file\";s:37:\"Screenshot-123012-741-PM-300x221.jpeg\";s:5:\"width\";i:300;s:6:\"height\";i:221;s:9:\"mime-type\";s:10:\"image/jpeg\";}s:14:\"post-thumbnail\";a:4:{s:4:\"file\";s:37:\"Screenshot-123012-741-PM-604x270.jpeg\";s:5:\"width\";i:604;s:6:\"height\";i:270;s:9:\"mime-type\";s:10:\"image/jpeg\";}}s:10:\"image_meta\";a:10:{s:8:\"aperture\";i:0;s:6:\"credit\";s:0:\"\";s:6:\"camera\";s:0:\"\";s:7:\"caption\";s:0:\"\";s:17:\"created_timestamp\";i:0;s:9:\"copyright\";s:0:\"\";s:12:\"focal_length\";i:0;s:3:\"iso\";i:0;s:13:\"shutter_speed\";i:0;s:5:\"title\";s:0:\"\";}}"
    }
},
{
    "model": "insp.wppostmeta",
    "pk": 36,
    "fields": {
        "post_id": 145,
        "meta_key": "_wp_attached_file",
        "meta_value": "2013/03/2013-03-15-18.47.58.jpg"
    }
},
{
    "model": "insp.wppostmeta",
    "pk": 37,
    "fields": {
        "post_id": 145,
        "meta_key": "_wp_attachment_metadata",
        "meta_value": "a:5:{s:5:\"width\";i:2592;s:6:\"height\";i:1936;s:4:\"file\";s:31:\"2013/03/2013-03-15-18.47.58.jpg\";s:5:\"sizes\";a:4:{s:9:\"thumbnail\";a:4:{s:4:\"file\";s:31:\"2013-03-15-18.47.58-150x150.jpg\";s:5:\"width\";i:150;s:6:\"height\";i:150;s:9:\"mime-type\";s:10:\"image/jpeg\";}s:6:\"medium\";a:4:{s:4:\"file\";s:31:\"2013-03-15-18.47.58-300x224.jpg\";s:5:\"width\";i:300;s:6:\"height\";i:224;s:9:\"mime-type\";s:10:\"image/jpeg\";}s:5:\"large\";a:4:{s:4:\"file\";s:32:\"2013-03-15-18.47.58-1024x764.jpg\";s:5:\"width\";i:1024;s:6:\"height\";i:764;s:9:\"mime-type\";s:10:\"image/jpeg\";}s:14:\"post-thumbnail\";a:4:{s:4:\"file\";s:31:\"2013-03-15-18.47.58-604x270.jpg\";s:5:\"width\";i:604;s:6:\"height\";i:270;s:9:\"mime-type\";s:10:\"image/jpeg\";}}s:10:\"image_meta\";a:10:{s:8:\"aperture\";i:0;s:6:\"credit\";s:0:\"\";s:6:\"camera\";s:8:\"iPhone 4\";s:7:\"caption\";s:0:\"\";s:17:\"created_timestamp\";i:1363373278;s:9:\"copyright\";s:0:\"\";s:12:\"focal_length\";s:4:\"3.85\";s:3:\"iso\";s:4:\"1000\";s:13:\"shutter_speed\";s:17:\"0.066666666666667\";s:5:\"title\";s:0:\"\";}}"
    }
},
{
    "model": "insp.wppostmeta",
    "pk": 38,
    "fields": {
        "post_id": 150,
        "meta_key": "_wp_attached_file",
        "meta_value": "2013/03/2013-03-22-13.09.13.jpg"
    }
},
{
    "model": "insp.wppostmeta",
    "pk": 39,
    "fields": {
        "post_id": 150,
        "meta_key": "_wp_attachment_metadata",
        "meta_value": "a:5:{s:5:\"width\";i:1936;s:6:\"height\";i:2592;s:4:\"file\";s:31:\"2013/03/2013-03-22-13.09.13.jpg\";s:5:\"sizes\";a:4:{s:9:\"thumbnail\";a:4:{s:4:\"file\";s:31:\"2013-03-22-13.09.13-150x150.jpg\";s:5:\"width\";i:150;s:6:\"height\";i:150;s:9:\"mime-type\";s:10:\"image/jpeg\";}s:6:\"medium\";a:4:{s:4:\"file\";s:31:\"2013-03-22-13.09.13-224x300.jpg\";s:5:\"width\";i:224;s:6:\"height\";i:300;s:9:\"mime-type\";s:10:\"image/jpeg\";}s:5:\"large\";a:4:{s:4:\"file\";s:32:\"2013-03-22-13.09.13-764x1024.jpg\";s:5:\"width\";i:764;s:6:\"height\";i:1024;s:9:\"mime-type\";s:10:\"image/jpeg\";}s:14:\"post-thumbnail\";a:4:{s:4:\"file\";s:31:\"2013-03-22-13.09.13-604x270.jpg\";s:5:\"width\";i:604;s:6:\"height\";i:270;s:9:\"mime-type\";s:10:\"image/jpeg\";}}s:10:\"image_meta\";a:10:{s:8:\"aperture\";i:0;s:6:\"credit\";s:0:\"\";s:6:\"camera\";s:8:\"iPhone 4\";s:7:\"caption\";s:0:\"\";s:17:\"created_timestamp\";i:1363957753;s:9:\"copyright\";s:0:\"\";s:12:\"focal_length\";s:4:\"3.85\";s:3:\"iso\";s:2:\"80\";s:13:\"shutter_speed\";s:17:\"0.033333333333333\";s:5:\"title\";s:0:\"\";}}"
    }
},
{
    "model": "insp.wppostmeta",
    "pk": 40,
    "fields": {
        "post_id": 153,
        "meta_key": "_wp_attached_file",
        "meta_value": "2013/03/2013-03-22-12.52.58.jpg"
    }
},
{
    "model": "insp.wppostmeta",
    "pk": 41,
    "fields": {
        "post_id": 153,
        "meta_key": "_wp_attachment_metadata",
        "meta_value": "a:5:{s:5:\"width\";i:2592;s:6:\"height\";i:1936;s:4:\"file\";s:31:\"2013/03/2013-03-22-12.52.58.jpg\";s:5:\"sizes\";a:4:{s:9:\"thumbnail\";a:4:{s:4:\"file\";s:31:\"2013-03-22-12.52.58-150x150.jpg\";s:5:\"width\";i:150;s:6:\"height\";i:150;s:9:\"mime-type\";s:10:\"image/jpeg\";}s:6:\"medium\";a:4:{s:4:\"file\";s:31:\"2013-03-22-12.52.58-300x224.jpg\";s:5:\"width\";i:300;s:6:\"height\";i:224;s:9:\"mime-type\";s:10:\"image/jpeg\";}s:5:\"large\";a:4:{s:4:\"file\";s:32:\"2013-03-22-12.52.58-1024x764.jpg\";s:5:\"width\";i:1024;s:6:\"height\";i:764;s:9:\"mime-type\";s:10:\"image/jpeg\";}s:14:\"post-thumbnail\";a:4:{s:4:\"file\";s:31:\"2013-03-22-12.52.58-604x270.jpg\";s:5:\"width\";i:604;s:6:\"height\";i:270;s:9:\"mime-type\";s:10:\"image/jpeg\";}}s:10:\"image_meta\";a:10:{s:8:\"aperture\";i:0;s:6:\"credit\";s:0:\"\";s:6:\"camera\";s:8:\"iPhone 4\";s:7:\"caption\";s:0:\"\";s:17:\"created_timestamp\";i:1363956778;s:9:\"copyright\";s:0:\"\";s:12:\"focal_length\";s:4:\"3.85\";s:3:\"iso\";s:3:\"320\";s:13:\"shutter_speed\";s:17:\"0.066666666666667\";s:5:\"title\";s:0:\"\";}}"
    }
},
{
    "model": "insp.wppostmeta",
    "pk": 42,
    "fields": {
        "post_id": 156,
        "meta_key": "_wp_attached_file",
        "meta_value": "2013/03/2013-03-22-15.45.39.jpg"
    }
},
{
    "model": "insp.wppostmeta",
    "pk": 43,
    "fields": {
        "post_id": 156,
        "meta_key": "_wp_attachment_metadata",
        "meta_value": "a:5:{s:5:\"width\";i:2592;s:6:\"height\";i:1936;s:4:\"file\";s:31:\"2013/03/2013-03-22-15.45.39.jpg\";s:5:\"sizes\";a:4:{s:9:\"thumbnail\";a:4:{s:4:\"file\";s:31:\"2013-03-22-15.45.39-150x150.jpg\";s:5:\"width\";i:150;s:6:\"height\";i:150;s:9:\"mime-type\";s:10:\"image/jpeg\";}s:6:\"medium\";a:4:{s:4:\"file\";s:31:\"2013-03-22-15.45.39-300x224.jpg\";s:5:\"width\";i:300;s:6:\"height\";i:224;s:9:\"mime-type\";s:10:\"image/jpeg\";}s:5:\"large\";a:4:{s:4:\"file\";s:32:\"2013-03-22-15.45.39-1024x764.jpg\";s:5:\"width\";i:1024;s:6:\"height\";i:764;s:9:\"mime-type\";s:10:\"image/jpeg\";}s:14:\"post-thumbnail\";a:4:{s:4:\"file\";s:31:\"2013-03-22-15.45.39-604x270.jpg\";s:5:\"width\";i:604;s:6:\"height\";i:270;s:9:\"mime-type\";s:10:\"image/jpeg\";}}s:10:\"image_meta\";a:10:{s:8:\"aperture\";i:0;s:6:\"credit\";s:0:\"\";s:6:\"camera\";s:8:\"iPhone 4\";s:7:\"caption\";s:0:\"\";s:17:\"created_timestamp\";i:1363967139;s:9:\"copyright\";s:0:\"\";s:12:\"focal_length\";s:4:\"3.85\";s:3:\"iso\";s:3:\"125\";s:13:\"shutter_speed\";s:18:\"0.0083333333333333\";s:5:\"title\";s:0:\"\";}}"
    }
},
{
    "model": "insp.wppostmeta",
    "pk": 44,
    "fields": {
        "post_id": 7,
        "meta_key": "_edit_last",
        "meta_value": "1"
    }
},
{
    "model": "insp.wppostmeta",
    "pk": 45,
    "fields": {
        "post_id": 9,
        "meta_key": "_edit_last",
        "meta_value": "1"
    }
},
{
    "model": "insp.wppostmeta",
    "pk": 46,
    "fields": {
        "post_id": 18,
        "meta_key": "_edit_last",
        "meta_value": "1"
    }
},
{
    "model": "insp.wppostmeta",
    "pk": 47,
    "fields": {
        "post_id": 18,
        "meta_key": "_wp_page_template",
        "meta_value": "default"
    }
},
{
    "model": "insp.wppostmeta",
    "pk": 48,
    "fields": {
        "post_id": 22,
        "meta_key": "_edit_last",
        "meta_value": "1"
    }
},
{
    "model": "insp.wppostmeta",
    "pk": 49,
    "fields": {
        "post_id": 79,
        "meta_key": "_edit_last",
        "meta_value": "1"
    }
},
{
    "model": "insp.wppostmeta",
    "pk": 50,
    "fields": {
        "post_id": 172,
        "meta_key": "_wp_attached_file",
        "meta_value": "2013/04/Screenshot-42013-451-AM.jpeg"
    }
},
{
    "model": "insp.wppostmeta",
    "pk": 51,
    "fields": {
        "post_id": 172,
        "meta_key": "_wp_attachment_metadata",
        "meta_value": "a:5:{s:5:\"width\";i:398;s:6:\"height\";i:226;s:4:\"file\";s:36:\"2013/04/Screenshot-42013-451-AM.jpeg\";s:5:\"sizes\";a:2:{s:9:\"thumbnail\";a:4:{s:4:\"file\";s:36:\"Screenshot-42013-451-AM-150x150.jpeg\";s:5:\"width\";i:150;s:6:\"height\";i:150;s:9:\"mime-type\";s:10:\"image/jpeg\";}s:6:\"medium\";a:4:{s:4:\"file\";s:36:\"Screenshot-42013-451-AM-300x170.jpeg\";s:5:\"width\";i:300;s:6:\"height\";i:170;s:9:\"mime-type\";s:10:\"image/jpeg\";}}s:10:\"image_meta\";a:10:{s:8:\"aperture\";i:0;s:6:\"credit\";s:0:\"\";s:6:\"camera\";s:0:\"\";s:7:\"caption\";s:0:\"\";s:17:\"created_timestamp\";i:0;s:9:\"copyright\";s:0:\"\";s:12:\"focal_length\";i:0;s:3:\"iso\";i:0;s:13:\"shutter_speed\";i:0;s:5:\"title\";s:0:\"\";}}"
    }
},
{
    "model": "insp.wppostmeta",
    "pk": 52,
    "fields": {
        "post_id": 176,
        "meta_key": "_wp_attached_file",
        "meta_value": "2013/04/Screenshot-43013-737-PM.jpeg"
    }
},
{
    "model": "insp.wppostmeta",
    "pk": 53,
    "fields": {
        "post_id": 176,
        "meta_key": "_wp_attachment_metadata",
        "meta_value": "a:5:{s:5:\"width\";i:355;s:6:\"height\";i:172;s:4:\"file\";s:36:\"2013/04/Screenshot-43013-737-PM.jpeg\";s:5:\"sizes\";a:2:{s:9:\"thumbnail\";a:4:{s:4:\"file\";s:36:\"Screenshot-43013-737-PM-150x150.jpeg\";s:5:\"width\";i:150;s:6:\"height\";i:150;s:9:\"mime-type\";s:10:\"image/jpeg\";}s:6:\"medium\";a:4:{s:4:\"file\";s:36:\"Screenshot-43013-737-PM-300x145.jpeg\";s:5:\"width\";i:300;s:6:\"height\";i:145;s:9:\"mime-type\";s:10:\"image/jpeg\";}}s:10:\"image_meta\";a:10:{s:8:\"aperture\";i:0;s:6:\"credit\";s:0:\"\";s:6:\"camera\";s:0:\"\";s:7:\"caption\";s:0:\"\";s:17:\"created_timestamp\";i:0;s:9:\"copyright\";s:0:\"\";s:12:\"focal_length\";i:0;s:3:\"iso\";i:0;s:13:\"shutter_speed\";i:0;s:5:\"title\";s:0:\"\";}}"
    }
},
{
    "model": "insp.wppostmeta",
    "pk": 54,
    "fields": {
        "post_id": 181,
        "meta_key": "_wp_attached_file",
        "meta_value": "2013/05/2013-05-08-06.27.43-2.jpg"
    }
},
{
    "model": "insp.wppostmeta",
    "pk": 55,
    "fields": {
        "post_id": 181,
        "meta_key": "_wp_attachment_metadata",
        "meta_value": "a:5:{s:5:\"width\";i:2342;s:6:\"height\";i:1150;s:4:\"file\";s:33:\"2013/05/2013-05-08-06.27.43-2.jpg\";s:5:\"sizes\";a:4:{s:9:\"thumbnail\";a:4:{s:4:\"file\";s:33:\"2013-05-08-06.27.43-2-150x150.jpg\";s:5:\"width\";i:150;s:6:\"height\";i:150;s:9:\"mime-type\";s:10:\"image/jpeg\";}s:6:\"medium\";a:4:{s:4:\"file\";s:33:\"2013-05-08-06.27.43-2-300x147.jpg\";s:5:\"width\";i:300;s:6:\"height\";i:147;s:9:\"mime-type\";s:10:\"image/jpeg\";}s:5:\"large\";a:4:{s:4:\"file\";s:34:\"2013-05-08-06.27.43-2-1024x502.jpg\";s:5:\"width\";i:1024;s:6:\"height\";i:502;s:9:\"mime-type\";s:10:\"image/jpeg\";}s:14:\"post-thumbnail\";a:4:{s:4:\"file\";s:33:\"2013-05-08-06.27.43-2-604x270.jpg\";s:5:\"width\";i:604;s:6:\"height\";i:270;s:9:\"mime-type\";s:10:\"image/jpeg\";}}s:10:\"image_meta\";a:10:{s:8:\"aperture\";i:0;s:6:\"credit\";s:0:\"\";s:6:\"camera\";s:8:\"iPhone 4\";s:7:\"caption\";s:0:\"\";s:17:\"created_timestamp\";i:1367994463;s:9:\"copyright\";s:0:\"\";s:12:\"focal_length\";s:4:\"3.85\";s:3:\"iso\";s:2:\"80\";s:13:\"shutter_speed\";s:5:\"0.025\";s:5:\"title\";s:0:\"\";}}"
    }
},
{
    "model": "insp.wppostmeta",
    "pk": 56,
    "fields": {
        "post_id": 188,
        "meta_key": "_wp_attached_file",
        "meta_value": "2013/05/2013-05-09-19.42.44-HDR.jpg"
    }
},
{
    "model": "insp.wppostmeta",
    "pk": 57,
    "fields": {
        "post_id": 188,
        "meta_key": "_wp_attachment_metadata",
        "meta_value": "a:5:{s:5:\"width\";i:2592;s:6:\"height\";i:1936;s:4:\"file\";s:35:\"2013/05/2013-05-09-19.42.44-HDR.jpg\";s:5:\"sizes\";a:4:{s:9:\"thumbnail\";a:4:{s:4:\"file\";s:35:\"2013-05-09-19.42.44-HDR-150x150.jpg\";s:5:\"width\";i:150;s:6:\"height\";i:150;s:9:\"mime-type\";s:10:\"image/jpeg\";}s:6:\"medium\";a:4:{s:4:\"file\";s:35:\"2013-05-09-19.42.44-HDR-300x224.jpg\";s:5:\"width\";i:300;s:6:\"height\";i:224;s:9:\"mime-type\";s:10:\"image/jpeg\";}s:5:\"large\";a:4:{s:4:\"file\";s:36:\"2013-05-09-19.42.44-HDR-1024x764.jpg\";s:5:\"width\";i:1024;s:6:\"height\";i:764;s:9:\"mime-type\";s:10:\"image/jpeg\";}s:14:\"post-thumbnail\";a:4:{s:4:\"file\";s:35:\"2013-05-09-19.42.44-HDR-604x270.jpg\";s:5:\"width\";i:604;s:6:\"height\";i:270;s:9:\"mime-type\";s:10:\"image/jpeg\";}}s:10:\"image_meta\";a:10:{s:8:\"aperture\";d:2.79999999999999982236431605997495353221893310546875;s:6:\"credit\";s:0:\"\";s:6:\"camera\";s:8:\"iPhone 4\";s:7:\"caption\";s:0:\"\";s:17:\"created_timestamp\";i:1368128564;s:9:\"copyright\";s:0:\"\";s:12:\"focal_length\";s:4:\"3.85\";s:3:\"iso\";s:3:\"100\";s:13:\"shutter_speed\";s:18:\"0.0083333333333333\";s:5:\"title\";s:0:\"\";}}"
    }
},
{
    "model": "insp.wppostmeta",
    "pk": 58,
    "fields": {
        "post_id": 193,
        "meta_key": "_wp_attached_file",
        "meta_value": "2013/05/2013-05-17-03.32.40.jpg"
    }
},
{
    "model": "insp.wppostmeta",
    "pk": 59,
    "fields": {
        "post_id": 193,
        "meta_key": "_wp_attachment_metadata",
        "meta_value": "a:5:{s:5:\"width\";i:2592;s:6:\"height\";i:1936;s:4:\"file\";s:31:\"2013/05/2013-05-17-03.32.40.jpg\";s:5:\"sizes\";a:4:{s:9:\"thumbnail\";a:4:{s:4:\"file\";s:31:\"2013-05-17-03.32.40-150x150.jpg\";s:5:\"width\";i:150;s:6:\"height\";i:150;s:9:\"mime-type\";s:10:\"image/jpeg\";}s:6:\"medium\";a:4:{s:4:\"file\";s:31:\"2013-05-17-03.32.40-300x224.jpg\";s:5:\"width\";i:300;s:6:\"height\";i:224;s:9:\"mime-type\";s:10:\"image/jpeg\";}s:5:\"large\";a:4:{s:4:\"file\";s:32:\"2013-05-17-03.32.40-1024x764.jpg\";s:5:\"width\";i:1024;s:6:\"height\";i:764;s:9:\"mime-type\";s:10:\"image/jpeg\";}s:14:\"post-thumbnail\";a:4:{s:4:\"file\";s:31:\"2013-05-17-03.32.40-604x270.jpg\";s:5:\"width\";i:604;s:6:\"height\";i:270;s:9:\"mime-type\";s:10:\"image/jpeg\";}}s:10:\"image_meta\";a:10:{s:8:\"aperture\";d:2.79999999999999982236431605997495353221893310546875;s:6:\"credit\";s:0:\"\";s:6:\"camera\";s:8:\"iPhone 4\";s:7:\"caption\";s:0:\"\";s:17:\"created_timestamp\";i:1368761560;s:9:\"copyright\";s:0:\"\";s:12:\"focal_length\";s:4:\"3.85\";s:3:\"iso\";s:2:\"80\";s:13:\"shutter_speed\";s:17:\"0.033333333333333\";s:5:\"title\";s:0:\"\";}}"
    }
},
{
    "model": "insp.wppostmeta",
    "pk": 60,
    "fields": {
        "post_id": 205,
        "meta_key": "_wp_attached_file",
        "meta_value": "2013/05/2013-05-18-17.20.20.jpg"
    }
},
{
    "model": "insp.wppostmeta",
    "pk": 61,
    "fields": {
        "post_id": 205,
        "meta_key": "_wp_attachment_metadata",
        "meta_value": "a:5:{s:5:\"width\";i:2592;s:6:\"height\";i:1936;s:4:\"file\";s:31:\"2013/05/2013-05-18-17.20.20.jpg\";s:5:\"sizes\";a:4:{s:9:\"thumbnail\";a:4:{s:4:\"file\";s:31:\"2013-05-18-17.20.20-150x150.jpg\";s:5:\"width\";i:150;s:6:\"height\";i:150;s:9:\"mime-type\";s:10:\"image/jpeg\";}s:6:\"medium\";a:4:{s:4:\"file\";s:31:\"2013-05-18-17.20.20-300x224.jpg\";s:5:\"width\";i:300;s:6:\"height\";i:224;s:9:\"mime-type\";s:10:\"image/jpeg\";}s:5:\"large\";a:4:{s:4:\"file\";s:32:\"2013-05-18-17.20.20-1024x764.jpg\";s:5:\"width\";i:1024;s:6:\"height\";i:764;s:9:\"mime-type\";s:10:\"image/jpeg\";}s:14:\"post-thumbnail\";a:4:{s:4:\"file\";s:31:\"2013-05-18-17.20.20-604x270.jpg\";s:5:\"width\";i:604;s:6:\"height\";i:270;s:9:\"mime-type\";s:10:\"image/jpeg\";}}s:10:\"image_meta\";a:10:{s:8:\"aperture\";d:2.79999999999999982236431605997495353221893310546875;s:6:\"credit\";s:0:\"\";s:6:\"camera\";s:8:\"iPhone 4\";s:7:\"caption\";s:0:\"\";s:17:\"created_timestamp\";i:1368897620;s:9:\"copyright\";s:0:\"\";s:12:\"focal_length\";s:4:\"3.85\";s:3:\"iso\";s:2:\"80\";s:13:\"shutter_speed\";s:4:\"0.02\";s:5:\"title\";s:0:\"\";}}"
    }
},
{
    "model": "insp.wppostmeta",
    "pk": 62,
    "fields": {
        "post_id": 209,
        "meta_key": "_wp_attached_file",
        "meta_value": "2013/06/968937_279133255557450_1583304586_n.jpg"
    }
},
{
    "model": "insp.wppostmeta",
    "pk": 63,
    "fields": {
        "post_id": 209,
        "meta_key": "_wp_attachment_metadata",
        "meta_value": "a:5:{s:5:\"width\";i:700;s:6:\"height\";i:395;s:4:\"file\";s:47:\"2013/06/968937_279133255557450_1583304586_n.jpg\";s:5:\"sizes\";a:3:{s:9:\"thumbnail\";a:4:{s:4:\"file\";s:47:\"968937_279133255557450_1583304586_n-150x150.jpg\";s:5:\"width\";i:150;s:6:\"height\";i:150;s:9:\"mime-type\";s:10:\"image/jpeg\";}s:6:\"medium\";a:4:{s:4:\"file\";s:47:\"968937_279133255557450_1583304586_n-300x169.jpg\";s:5:\"width\";i:300;s:6:\"height\";i:169;s:9:\"mime-type\";s:10:\"image/jpeg\";}s:14:\"post-thumbnail\";a:4:{s:4:\"file\";s:47:\"968937_279133255557450_1583304586_n-604x270.jpg\";s:5:\"width\";i:604;s:6:\"height\";i:270;s:9:\"mime-type\";s:10:\"image/jpeg\";}}s:10:\"image_meta\";a:10:{s:8:\"aperture\";i:0;s:6:\"credit\";s:0:\"\";s:6:\"camera\";s:0:\"\";s:7:\"caption\";s:0:\"\";s:17:\"created_timestamp\";i:0;s:9:\"copyright\";s:0:\"\";s:12:\"focal_length\";i:0;s:3:\"iso\";i:0;s:13:\"shutter_speed\";i:0;s:5:\"title\";s:0:\"\";}}"
    }
},
{
    "model": "insp.wppostmeta",
    "pk": 64,
    "fields": {
        "post_id": 212,
        "meta_key": "_wp_attached_file",
        "meta_value": "2013/06/t1tl0s_f0t0gr4f1as.jpg"
    }
},
{
    "model": "insp.wppostmeta",
    "pk": 65,
    "fields": {
        "post_id": 212,
        "meta_key": "_wp_attachment_metadata",
        "meta_value": "a:5:{s:5:\"width\";i:571;s:6:\"height\";i:859;s:4:\"file\";s:30:\"2013/06/t1tl0s_f0t0gr4f1as.jpg\";s:5:\"sizes\";a:3:{s:9:\"thumbnail\";a:4:{s:4:\"file\";s:30:\"t1tl0s_f0t0gr4f1as-150x150.jpg\";s:5:\"width\";i:150;s:6:\"height\";i:150;s:9:\"mime-type\";s:10:\"image/jpeg\";}s:6:\"medium\";a:4:{s:4:\"file\";s:30:\"t1tl0s_f0t0gr4f1as-199x300.jpg\";s:5:\"width\";i:199;s:6:\"height\";i:300;s:9:\"mime-type\";s:10:\"image/jpeg\";}s:14:\"post-thumbnail\";a:4:{s:4:\"file\";s:30:\"t1tl0s_f0t0gr4f1as-571x270.jpg\";s:5:\"width\";i:571;s:6:\"height\";i:270;s:9:\"mime-type\";s:10:\"image/jpeg\";}}s:10:\"image_meta\";a:10:{s:8:\"aperture\";i:0;s:6:\"credit\";s:0:\"\";s:6:\"camera\";s:0:\"\";s:7:\"caption\";s:0:\"\";s:17:\"created_timestamp\";i:0;s:9:\"copyright\";s:0:\"\";s:12:\"focal_length\";i:0;s:3:\"iso\";i:0;s:13:\"shutter_speed\";i:0;s:5:\"title\";s:0:\"\";}}"
    }
},
{
    "model": "insp.wppostmeta",
    "pk": 66,
    "fields": {
        "post_id": 226,
        "meta_key": "_wp_attached_file",
        "meta_value": "2013/07/easter_egg.jpeg"
    }
},
{
    "model": "insp.wppostmeta",
    "pk": 67,
    "fields": {
        "post_id": 226,
        "meta_key": "_wp_attachment_metadata",
        "meta_value": "a:5:{s:5:\"width\";i:923;s:6:\"height\";i:389;s:4:\"file\";s:23:\"2013/07/easter_egg.jpeg\";s:5:\"sizes\";a:3:{s:9:\"thumbnail\";a:4:{s:4:\"file\";s:23:\"easter_egg-150x150.jpeg\";s:5:\"width\";i:150;s:6:\"height\";i:150;s:9:\"mime-type\";s:10:\"image/jpeg\";}s:6:\"medium\";a:4:{s:4:\"file\";s:23:\"easter_egg-300x126.jpeg\";s:5:\"width\";i:300;s:6:\"height\";i:126;s:9:\"mime-type\";s:10:\"image/jpeg\";}s:14:\"post-thumbnail\";a:4:{s:4:\"file\";s:23:\"easter_egg-604x270.jpeg\";s:5:\"width\";i:604;s:6:\"height\";i:270;s:9:\"mime-type\";s:10:\"image/jpeg\";}}s:10:\"image_meta\";a:10:{s:8:\"aperture\";i:0;s:6:\"credit\";s:0:\"\";s:6:\"camera\";s:0:\"\";s:7:\"caption\";s:0:\"\";s:17:\"created_timestamp\";i:0;s:9:\"copyright\";s:0:\"\";s:12:\"focal_length\";i:0;s:3:\"iso\";i:0;s:13:\"shutter_speed\";i:0;s:5:\"title\";s:0:\"\";}}"
    }
},
{
    "model": "insp.wppostmeta",
    "pk": 68,
    "fields": {
        "post_id": 232,
        "meta_key": "_wp_attached_file",
        "meta_value": "2013/07/2013-07-26-00.06.23.jpg"
    }
},
{
    "model": "insp.wppostmeta",
    "pk": 69,
    "fields": {
        "post_id": 232,
        "meta_key": "_wp_attachment_metadata",
        "meta_value": "a:5:{s:5:\"width\";i:2592;s:6:\"height\";i:1936;s:4:\"file\";s:31:\"2013/07/2013-07-26-00.06.23.jpg\";s:5:\"sizes\";a:4:{s:9:\"thumbnail\";a:4:{s:4:\"file\";s:31:\"2013-07-26-00.06.23-150x150.jpg\";s:5:\"width\";i:150;s:6:\"height\";i:150;s:9:\"mime-type\";s:10:\"image/jpeg\";}s:6:\"medium\";a:4:{s:4:\"file\";s:31:\"2013-07-26-00.06.23-300x224.jpg\";s:5:\"width\";i:300;s:6:\"height\";i:224;s:9:\"mime-type\";s:10:\"image/jpeg\";}s:5:\"large\";a:4:{s:4:\"file\";s:32:\"2013-07-26-00.06.23-1024x764.jpg\";s:5:\"width\";i:1024;s:6:\"height\";i:764;s:9:\"mime-type\";s:10:\"image/jpeg\";}s:14:\"post-thumbnail\";a:4:{s:4:\"file\";s:31:\"2013-07-26-00.06.23-604x270.jpg\";s:5:\"width\";i:604;s:6:\"height\";i:270;s:9:\"mime-type\";s:10:\"image/jpeg\";}}s:10:\"image_meta\";a:10:{s:8:\"aperture\";d:2.79999999999999982236431605997495353221893310546875;s:6:\"credit\";s:0:\"\";s:6:\"camera\";s:8:\"iPhone 4\";s:7:\"caption\";s:0:\"\";s:17:\"created_timestamp\";i:1374797183;s:9:\"copyright\";s:0:\"\";s:12:\"focal_length\";s:4:\"3.85\";s:3:\"iso\";s:4:\"1000\";s:13:\"shutter_speed\";s:17:\"0.066666666666667\";s:5:\"title\";s:0:\"\";}}"
    }
},
{
    "model": "insp.wppostmeta",
    "pk": 70,
    "fields": {
        "post_id": 234,
        "meta_key": "_wp_attached_file",
        "meta_value": "2013/07/defense.jpg"
    }
},
{
    "model": "insp.wppostmeta",
    "pk": 71,
    "fields": {
        "post_id": 234,
        "meta_key": "_wp_attachment_metadata",
        "meta_value": "a:5:{s:5:\"width\";i:1936;s:6:\"height\";i:2592;s:4:\"file\";s:19:\"2013/07/defense.jpg\";s:5:\"sizes\";a:4:{s:9:\"thumbnail\";a:4:{s:4:\"file\";s:19:\"defense-150x150.jpg\";s:5:\"width\";i:150;s:6:\"height\";i:150;s:9:\"mime-type\";s:10:\"image/jpeg\";}s:6:\"medium\";a:4:{s:4:\"file\";s:19:\"defense-224x300.jpg\";s:5:\"width\";i:224;s:6:\"height\";i:300;s:9:\"mime-type\";s:10:\"image/jpeg\";}s:5:\"large\";a:4:{s:4:\"file\";s:20:\"defense-764x1024.jpg\";s:5:\"width\";i:764;s:6:\"height\";i:1024;s:9:\"mime-type\";s:10:\"image/jpeg\";}s:14:\"post-thumbnail\";a:4:{s:4:\"file\";s:19:\"defense-604x270.jpg\";s:5:\"width\";i:604;s:6:\"height\";i:270;s:9:\"mime-type\";s:10:\"image/jpeg\";}}s:10:\"image_meta\";a:10:{s:8:\"aperture\";d:2.79999999999999982236431605997495353221893310546875;s:6:\"credit\";s:0:\"\";s:6:\"camera\";s:8:\"iPhone 4\";s:7:\"caption\";s:0:\"\";s:17:\"created_timestamp\";i:1374797377;s:9:\"copyright\";s:0:\"\";s:12:\"focal_length\";s:4:\"3.85\";s:3:\"iso\";s:3:\"400\";s:13:\"shutter_speed\";s:17:\"0.066666666666667\";s:5:\"title\";s:0:\"\";}}"
    }
},
{
    "model": "insp.wppostmeta",
    "pk": 72,
    "fields": {
        "post_id": 242,
        "meta_key": "_wp_attached_file",
        "meta_value": "2013/08/4th.jpeg"
    }
},
{
    "model": "insp.wppostmeta",
    "pk": 73,
    "fields": {
        "post_id": 242,
        "meta_key": "_wp_attachment_metadata",
        "meta_value": "a:5:{s:5:\"width\";i:734;s:6:\"height\";i:255;s:4:\"file\";s:16:\"2013/08/4th.jpeg\";s:5:\"sizes\";a:3:{s:9:\"thumbnail\";a:4:{s:4:\"file\";s:16:\"4th-150x150.jpeg\";s:5:\"width\";i:150;s:6:\"height\";i:150;s:9:\"mime-type\";s:10:\"image/jpeg\";}s:6:\"medium\";a:4:{s:4:\"file\";s:16:\"4th-300x104.jpeg\";s:5:\"width\";i:300;s:6:\"height\";i:104;s:9:\"mime-type\";s:10:\"image/jpeg\";}s:14:\"post-thumbnail\";a:4:{s:4:\"file\";s:16:\"4th-604x255.jpeg\";s:5:\"width\";i:604;s:6:\"height\";i:255;s:9:\"mime-type\";s:10:\"image/jpeg\";}}s:10:\"image_meta\";a:10:{s:8:\"aperture\";i:0;s:6:\"credit\";s:0:\"\";s:6:\"camera\";s:0:\"\";s:7:\"caption\";s:0:\"\";s:17:\"created_timestamp\";i:0;s:9:\"copyright\";s:0:\"\";s:12:\"focal_length\";i:0;s:3:\"iso\";i:0;s:13:\"shutter_speed\";i:0;s:5:\"title\";s:0:\"\";}}"
    }
},
{
    "model": "insp.wppostmeta",
    "pk": 74,
    "fields": {
        "post_id": 246,
        "meta_key": "_wp_attached_file",
        "meta_value": "2013/08/font_metrics.jpeg"
    }
},
{
    "model": "insp.wppostmeta",
    "pk": 75,
    "fields": {
        "post_id": 246,
        "meta_key": "_wp_attachment_metadata",
        "meta_value": "a:5:{s:5:\"width\";i:852;s:6:\"height\";i:463;s:4:\"file\";s:25:\"2013/08/font_metrics.jpeg\";s:5:\"sizes\";a:3:{s:9:\"thumbnail\";a:4:{s:4:\"file\";s:25:\"font_metrics-150x150.jpeg\";s:5:\"width\";i:150;s:6:\"height\";i:150;s:9:\"mime-type\";s:10:\"image/jpeg\";}s:6:\"medium\";a:4:{s:4:\"file\";s:25:\"font_metrics-300x163.jpeg\";s:5:\"width\";i:300;s:6:\"height\";i:163;s:9:\"mime-type\";s:10:\"image/jpeg\";}s:14:\"post-thumbnail\";a:4:{s:4:\"file\";s:25:\"font_metrics-604x270.jpeg\";s:5:\"width\";i:604;s:6:\"height\";i:270;s:9:\"mime-type\";s:10:\"image/jpeg\";}}s:10:\"image_meta\";a:10:{s:8:\"aperture\";i:0;s:6:\"credit\";s:0:\"\";s:6:\"camera\";s:0:\"\";s:7:\"caption\";s:0:\"\";s:17:\"created_timestamp\";i:0;s:9:\"copyright\";s:0:\"\";s:12:\"focal_length\";i:0;s:3:\"iso\";i:0;s:13:\"shutter_speed\";i:0;s:5:\"title\";s:0:\"\";}}"
    }
},
{
    "model": "insp.wppostmeta",
    "pk": 76,
    "fields": {
        "post_id": 251,
        "meta_key": "_wp_attached_file",
        "meta_value": "2013/08/hitler_jesus.jpg"
    }
},
{
    "model": "insp.wppostmeta",
    "pk": 77,
    "fields": {
        "post_id": 251,
        "meta_key": "_wp_attachment_metadata",
        "meta_value": "a:5:{s:5:\"width\";i:700;s:6:\"height\";i:465;s:4:\"file\";s:24:\"2013/08/hitler_jesus.jpg\";s:5:\"sizes\";a:3:{s:9:\"thumbnail\";a:4:{s:4:\"file\";s:24:\"hitler_jesus-150x150.jpg\";s:5:\"width\";i:150;s:6:\"height\";i:150;s:9:\"mime-type\";s:10:\"image/jpeg\";}s:6:\"medium\";a:4:{s:4:\"file\";s:24:\"hitler_jesus-300x199.jpg\";s:5:\"width\";i:300;s:6:\"height\";i:199;s:9:\"mime-type\";s:10:\"image/jpeg\";}s:14:\"post-thumbnail\";a:4:{s:4:\"file\";s:24:\"hitler_jesus-604x270.jpg\";s:5:\"width\";i:604;s:6:\"height\";i:270;s:9:\"mime-type\";s:10:\"image/jpeg\";}}s:10:\"image_meta\";a:10:{s:8:\"aperture\";i:0;s:6:\"credit\";s:0:\"\";s:6:\"camera\";s:0:\"\";s:7:\"caption\";s:0:\"\";s:17:\"created_timestamp\";i:0;s:9:\"copyright\";s:0:\"\";s:12:\"focal_length\";i:0;s:3:\"iso\";i:0;s:13:\"shutter_speed\";i:0;s:5:\"title\";s:0:\"\";}}"
    }
},
{
    "model": "insp.wppostmeta",
    "pk": 78,
    "fields": {
        "post_id": 37,
        "meta_key": "_edit_last",
        "meta_value": "1"
    }
},
{
    "model": "insp.wppostmeta",
    "pk": 79,
    "fields": {
        "post_id": 42,
        "meta_key": "_edit_last",
        "meta_value": "1"
    }
},
{
    "model": "insp.wppostmeta",
    "pk": 80,
    "fields": {
        "post_id": 47,
        "meta_key": "_edit_last",
        "meta_value": "1"
    }
},
{
    "model": "insp.wppostmeta",
    "pk": 81,
    "fields": {
        "post_id": 51,
        "meta_key": "_edit_last",
        "meta_value": "1"
    }
},
{
    "model": "insp.wppostmeta",
    "pk": 82,
    "fields": {
        "post_id": 55,
        "meta_key": "_edit_last",
        "meta_value": "1"
    }
},
{
    "model": "insp.wppostmeta",
    "pk": 83,
    "fields": {
        "post_id": 64,
        "meta_key": "_edit_last",
        "meta_value": "1"
    }
},
{
    "model": "insp.wppostmeta",
    "pk": 84,
    "fields": {
        "post_id": 69,
        "meta_key": "_edit_last",
        "meta_value": "1"
    }
},
{
    "model": "insp.wppostmeta",
    "pk": 85,
    "fields": {
        "post_id": 73,
        "meta_key": "_edit_last",
        "meta_value": "1"
    }
},
{
    "model": "insp.wppostmeta",
    "pk": 86,
    "fields": {
        "post_id": 94,
        "meta_key": "_edit_last",
        "meta_value": "1"
    }
},
{
    "model": "insp.wppostmeta",
    "pk": 87,
    "fields": {
        "post_id": 97,
        "meta_key": "_edit_last",
        "meta_value": "1"
    }
},
{
    "model": "insp.wppostmeta",
    "pk": 88,
    "fields": {
        "post_id": 99,
        "meta_key": "_edit_last",
        "meta_value": "1"
    }
},
{
    "model": "insp.wppostmeta",
    "pk": 89,
    "fields": {
        "post_id": 104,
        "meta_key": "_edit_last",
        "meta_value": "1"
    }
},
{
    "model": "insp.wppostmeta",
    "pk": 90,
    "fields": {
        "post_id": 111,
        "meta_key": "_edit_last",
        "meta_value": "1"
    }
},
{
    "model": "insp.wppostmeta",
    "pk": 91,
    "fields": {
        "post_id": 114,
        "meta_key": "_edit_last",
        "meta_value": "1"
    }
},
{
    "model": "insp.wppostmeta",
    "pk": 92,
    "fields": {
        "post_id": 120,
        "meta_key": "_edit_last",
        "meta_value": "1"
    }
},
{
    "model": "insp.wppostmeta",
    "pk": 93,
    "fields": {
        "post_id": 122,
        "meta_key": "_edit_last",
        "meta_value": "1"
    }
},
{
    "model": "insp.wppostmeta",
    "pk": 94,
    "fields": {
        "post_id": 127,
        "meta_key": "_edit_last",
        "meta_value": "1"
    }
},
{
    "model": "insp.wppostmeta",
    "pk": 95,
    "fields": {
        "post_id": 130,
        "meta_key": "_edit_last",
        "meta_value": "1"
    }
},
{
    "model": "insp.wppostmeta",
    "pk": 96,
    "fields": {
        "post_id": 141,
        "meta_key": "_edit_last",
        "meta_value": "1"
    }
},
{
    "model": "insp.wppostmeta",
    "pk": 97,
    "fields": {
        "post_id": 144,
        "meta_key": "_edit_last",
        "meta_value": "1"
    }
},
{
    "model": "insp.wppostmeta",
    "pk": 98,
    "fields": {
        "post_id": 149,
        "meta_key": "_edit_last",
        "meta_value": "1"
    }
},
{
    "model": "insp.wppostmeta",
    "pk": 99,
    "fields": {
        "post_id": 152,
        "meta_key": "_edit_last",
        "meta_value": "1"
    }
},
{
    "model": "insp.wppostmeta",
    "pk": 100,
    "fields": {
        "post_id": 155,
        "meta_key": "_edit_last",
        "meta_value": "1"
    }
},
{
    "model": "insp.wppostmeta",
    "pk": 101,
    "fields": {
        "post_id": 158,
        "meta_key": "_edit_last",
        "meta_value": "1"
    }
},
{
    "model": "insp.wppostmeta",
    "pk": 102,
    "fields": {
        "post_id": 165,
        "meta_key": "_wp_jd_target",
        "meta_value": "http://ozmaxplanet.com/blog/fun-fact-2-why-we-play-games/"
    }
},
{
    "model": "insp.wppostmeta",
    "pk": 103,
    "fields": {
        "post_id": 165,
        "meta_key": "_edit_last",
        "meta_value": "1"
    }
},
{
    "model": "insp.wppostmeta",
    "pk": 104,
    "fields": {
        "post_id": 165,
        "meta_key": "_jd_tweet_this",
        "meta_value": "yes"
    }
},
{
    "model": "insp.wppostmeta",
    "pk": 105,
    "fields": {
        "post_id": 165,
        "meta_key": "_wp_jd_wp",
        "meta_value": "http://ozmaxplanet.com/blog/?p=165"
    }
},
{
    "model": "insp.wppostmeta",
    "pk": 106,
    "fields": {
        "post_id": 165,
        "meta_key": "_wpt_failed",
        "meta_value": "a:5:{s:6:\"author\";b:0;s:8:\"sentence\";s:74:\"New post: Fun Fact #2 Why we play games http://ozmaxplanet.com/blog/?p=165\";s:5:\"error\";s:50:\"This account is not authorized to post to Twitter.\";s:4:\"code\";i:401;s:9:\"timestamp\";i:1364337213;}"
    }
},
{
    "model": "insp.wppostmeta",
    "pk": 107,
    "fields": {
        "post_id": 165,
        "meta_key": "_wpt_failed",
        "meta_value": "a:5:{s:6:\"author\";b:0;s:8:\"sentence\";s:74:\"New post: Fun Fact #2 Why we play games http://ozmaxplanet.com/blog/?p=165\";s:5:\"error\";s:50:\"This account is not authorized to post to Twitter.\";s:4:\"code\";i:401;s:9:\"timestamp\";i:1364337235;}"
    }
},
{
    "model": "insp.wppostmeta",
    "pk": 108,
    "fields": {
        "post_id": 165,
        "meta_key": "_wpt_failed",
        "meta_value": "a:5:{s:6:\"author\";b:0;s:8:\"sentence\";s:80:\"Post Edited: Fun Fact #2 Why do we play games http://ozmaxplanet.com/blog/?p=165\";s:5:\"error\";s:50:\"This account is not authorized to post to Twitter.\";s:4:\"code\";i:401;s:9:\"timestamp\";i:1364337272;}"
    }
},
{
    "model": "insp.wppostmeta",
    "pk": 109,
    "fields": {
        "post_id": 165,
        "meta_key": "_wpt_failed",
        "meta_value": "a:5:{s:6:\"author\";b:0;s:8:\"sentence\";s:80:\"Post Edited: Fun Fact #2 Why do we play games http://ozmaxplanet.com/blog/?p=165\";s:5:\"error\";s:50:\"This account is not authorized to post to Twitter.\";s:4:\"code\";i:401;s:9:\"timestamp\";i:1364337276;}"
    }
},
{
    "model": "insp.wppostmeta",
    "pk": 110,
    "fields": {
        "post_id": 171,
        "meta_key": "_edit_last",
        "meta_value": "1"
    }
},
{
    "model": "insp.wppostmeta",
    "pk": 111,
    "fields": {
        "post_id": 175,
        "meta_key": "_edit_last",
        "meta_value": "1"
    }
},
{
    "model": "insp.wppostmeta",
    "pk": 112,
    "fields": {
        "post_id": 180,
        "meta_key": "_edit_last",
        "meta_value": "1"
    }
},
{
    "model": "insp.wppostmeta",
    "pk": 113,
    "fields": {
        "post_id": 187,
        "meta_key": "_edit_last",
        "meta_value": "1"
    }
},
{
    "model": "insp.wppostmeta",
    "pk": 114,
    "fields": {
        "post_id": 191,
        "meta_key": "_edit_last",
        "meta_value": "1"
    }
},
{
    "model": "insp.wppostmeta",
    "pk": 115,
    "fields": {
        "post_id": 201,
        "meta_key": "_edit_last",
        "meta_value": "1"
    }
},
{
    "model": "insp.wppostmeta",
    "pk": 116,
    "fields": {
        "post_id": 204,
        "meta_key": "_edit_last",
        "meta_value": "1"
    }
},
{
    "model": "insp.wppostmeta",
    "pk": 117,
    "fields": {
        "post_id": 208,
        "meta_key": "_edit_last",
        "meta_value": "1"
    }
},
{
    "model": "insp.wppostmeta",
    "pk": 118,
    "fields": {
        "post_id": 211,
        "meta_key": "_edit_last",
        "meta_value": "1"
    }
},
{
    "model": "insp.wppostmeta",
    "pk": 119,
    "fields": {
        "post_id": 216,
        "meta_key": "_edit_last",
        "meta_value": "1"
    }
},
{
    "model": "insp.wppostmeta",
    "pk": 120,
    "fields": {
        "post_id": 225,
        "meta_key": "_edit_last",
        "meta_value": "1"
    }
},
{
    "model": "insp.wppostmeta",
    "pk": 121,
    "fields": {
        "post_id": 231,
        "meta_key": "_edit_last",
        "meta_value": "1"
    }
},
{
    "model": "insp.wppostmeta",
    "pk": 122,
    "fields": {
        "post_id": 238,
        "meta_key": "_edit_last",
        "meta_value": "1"
    }
},
{
    "model": "insp.wppostmeta",
    "pk": 123,
    "fields": {
        "post_id": 241,
        "meta_key": "_edit_last",
        "meta_value": "1"
    }
},
{
    "model": "insp.wppostmeta",
    "pk": 124,
    "fields": {
        "post_id": 245,
        "meta_key": "_edit_last",
        "meta_value": "1"
    }
},
{
    "model": "insp.wppostmeta",
    "pk": 125,
    "fields": {
        "post_id": 250,
        "meta_key": "_edit_last",
        "meta_value": "1"
    }
},
{
    "model": "insp.wppostmeta",
    "pk": 126,
    "fields": {
        "post_id": 252,
        "meta_key": "_wp_attached_file",
        "meta_value": "2013/09/bg.jpg"
    }
},
{
    "model": "insp.wppostmeta",
    "pk": 127,
    "fields": {
        "post_id": 252,
        "meta_key": "_wp_attachment_context",
        "meta_value": "custom-background"
    }
},
{
    "model": "insp.wppostmeta",
    "pk": 128,
    "fields": {
        "post_id": 252,
        "meta_key": "_wp_attachment_metadata",
        "meta_value": "a:5:{s:5:\"width\";i:1920;s:6:\"height\";i:1080;s:4:\"file\";s:14:\"2013/09/bg.jpg\";s:5:\"sizes\";a:4:{s:9:\"thumbnail\";a:4:{s:4:\"file\";s:14:\"bg-150x150.jpg\";s:5:\"width\";i:150;s:6:\"height\";i:150;s:9:\"mime-type\";s:10:\"image/jpeg\";}s:6:\"medium\";a:4:{s:4:\"file\";s:14:\"bg-300x168.jpg\";s:5:\"width\";i:300;s:6:\"height\";i:168;s:9:\"mime-type\";s:10:\"image/jpeg\";}s:5:\"large\";a:4:{s:4:\"file\";s:15:\"bg-1024x576.jpg\";s:5:\"width\";i:1024;s:6:\"height\";i:576;s:9:\"mime-type\";s:10:\"image/jpeg\";}s:14:\"post-thumbnail\";a:4:{s:4:\"file\";s:14:\"bg-940x198.jpg\";s:5:\"width\";i:940;s:6:\"height\";i:198;s:9:\"mime-type\";s:10:\"image/jpeg\";}}s:10:\"image_meta\";a:10:{s:8:\"aperture\";i:0;s:6:\"credit\";s:0:\"\";s:6:\"camera\";s:0:\"\";s:7:\"caption\";s:0:\"\";s:17:\"created_timestamp\";i:0;s:9:\"copyright\";s:0:\"\";s:12:\"focal_length\";i:0;s:3:\"iso\";i:0;s:13:\"shutter_speed\";i:0;s:5:\"title\";s:0:\"\";}}"
    }
},
{
    "model": "insp.wppostmeta",
    "pk": 129,
    "fields": {
        "post_id": 252,
        "meta_key": "_wp_attachment_is_custom_background",
        "meta_value": "ozmaxplanettheme"
    }
},
{
    "model": "insp.wppostmeta",
    "pk": 135,
    "fields": {
        "post_id": 255,
        "meta_key": "_wp_attached_file",
        "meta_value": "2013/09/bg1.jpg"
    }
},
{
    "model": "insp.wppostmeta",
    "pk": 136,
    "fields": {
        "post_id": 255,
        "meta_key": "_wp_attachment_context",
        "meta_value": "custom-background"
    }
},
{
    "model": "insp.wppostmeta",
    "pk": 137,
    "fields": {
        "post_id": 255,
        "meta_key": "_wp_attachment_metadata",
        "meta_value": "a:5:{s:5:\"width\";i:1920;s:6:\"height\";i:1080;s:4:\"file\";s:15:\"2013/09/bg1.jpg\";s:5:\"sizes\";a:4:{s:9:\"thumbnail\";a:4:{s:4:\"file\";s:15:\"bg1-150x150.jpg\";s:5:\"width\";i:150;s:6:\"height\";i:150;s:9:\"mime-type\";s:10:\"image/jpeg\";}s:6:\"medium\";a:4:{s:4:\"file\";s:15:\"bg1-300x168.jpg\";s:5:\"width\";i:300;s:6:\"height\";i:168;s:9:\"mime-type\";s:10:\"image/jpeg\";}s:5:\"large\";a:4:{s:4:\"file\";s:16:\"bg1-1024x576.jpg\";s:5:\"width\";i:1024;s:6:\"height\";i:576;s:9:\"mime-type\";s:10:\"image/jpeg\";}s:14:\"post-thumbnail\";a:4:{s:4:\"file\";s:15:\"bg1-940x198.jpg\";s:5:\"width\";i:940;s:6:\"height\";i:198;s:9:\"mime-type\";s:10:\"image/jpeg\";}}s:10:\"image_meta\";a:10:{s:8:\"aperture\";i:0;s:6:\"credit\";s:0:\"\";s:6:\"camera\";s:0:\"\";s:7:\"caption\";s:0:\"\";s:17:\"created_timestamp\";i:0;s:9:\"copyright\";s:0:\"\";s:12:\"focal_length\";i:0;s:3:\"iso\";i:0;s:13:\"shutter_speed\";i:0;s:5:\"title\";s:0:\"\";}}"
    }
},
{
    "model": "insp.wppostmeta",
    "pk": 138,
    "fields": {
        "post_id": 255,
        "meta_key": "_wp_attachment_is_custom_background",
        "meta_value": "ozmaxplanettheme"
    }
},
{
    "model": "insp.wppostmeta",
    "pk": 139,
    "fields": {
        "post_id": 246,
        "meta_key": "_edit_lock",
        "meta_value": "1380575377:1"
    }
},
{
    "model": "insp.wppostmeta",
    "pk": 140,
    "fields": {
        "post_id": 255,
        "meta_key": "_edit_lock",
        "meta_value": "1380575317:1"
    }
},
{
    "model": "insp.wppostmeta",
    "pk": 143,
    "fields": {
        "post_id": 257,
        "meta_key": "_wp_attached_file",
        "meta_value": "2013/10/64239-21346.jpg"
    }
},
{
    "model": "insp.wppostmeta",
    "pk": 144,
    "fields": {
        "post_id": 257,
        "meta_key": "_wp_attachment_metadata",
        "meta_value": "a:5:{s:5:\"width\";i:1600;s:6:\"height\";i:1200;s:4:\"file\";s:23:\"2013/10/64239-21346.jpg\";s:5:\"sizes\";a:4:{s:9:\"thumbnail\";a:4:{s:4:\"file\";s:23:\"64239-21346-150x150.jpg\";s:5:\"width\";i:150;s:6:\"height\";i:150;s:9:\"mime-type\";s:10:\"image/jpeg\";}s:6:\"medium\";a:4:{s:4:\"file\";s:23:\"64239-21346-300x225.jpg\";s:5:\"width\";i:300;s:6:\"height\";i:225;s:9:\"mime-type\";s:10:\"image/jpeg\";}s:5:\"large\";a:4:{s:4:\"file\";s:24:\"64239-21346-1024x768.jpg\";s:5:\"width\";i:1024;s:6:\"height\";i:768;s:9:\"mime-type\";s:10:\"image/jpeg\";}s:14:\"post-thumbnail\";a:4:{s:4:\"file\";s:23:\"64239-21346-940x198.jpg\";s:5:\"width\";i:940;s:6:\"height\";i:198;s:9:\"mime-type\";s:10:\"image/jpeg\";}}s:10:\"image_meta\";a:10:{s:8:\"aperture\";i:0;s:6:\"credit\";s:0:\"\";s:6:\"camera\";s:0:\"\";s:7:\"caption\";s:0:\"\";s:17:\"created_timestamp\";i:0;s:9:\"copyright\";s:0:\"\";s:12:\"focal_length\";i:0;s:3:\"iso\";i:0;s:13:\"shutter_speed\";i:0;s:5:\"title\";s:0:\"\";}}"
    }
},
{
    "model": "insp.wppostmeta",
    "pk": 149,
    "fields": {
        "post_id": 262,
        "meta_key": "_edit_last",
        "meta_value": "1"
    }
},
{
    "model": "insp.wppostmeta",
    "pk": 150,
    "fields": {
        "post_id": 262,
        "meta_key": "_edit_lock",
        "meta_value": "1383414050:1"
    }
},
{
    "model": "insp.wppostmeta",
    "pk": 153,
    "fields": {
        "post_id": 264,
        "meta_key": "_edit_last",
        "meta_value": "1"
    }
},
{
    "model": "insp.wppostmeta",
    "pk": 154,
    "fields": {
        "post_id": 264,
        "meta_key": "_edit_lock",
        "meta_value": "1383912181:1"
    }
},
{
    "model": "insp.wppostmeta",
    "pk": 157,
    "fields": {
        "post_id": 267,
        "meta_key": "_edit_last",
        "meta_value": "1"
    }
},
{
    "model": "insp.wppostmeta",
    "pk": 158,
    "fields": {
        "post_id": 267,
        "meta_key": "_edit_lock",
        "meta_value": "1384296757:1"
    }
},
{
    "model": "insp.wppostmeta",
    "pk": 161,
    "fields": {
        "post_id": 271,
        "meta_key": "_edit_last",
        "meta_value": "1"
    }
},
{
    "model": "insp.wppostmeta",
    "pk": 162,
    "fields": {
        "post_id": 271,
        "meta_key": "_edit_lock",
        "meta_value": "1386807763:1"
    }
},
{
    "model": "insp.wppostmeta",
    "pk": 167,
    "fields": {
        "post_id": 276,
        "meta_key": "_edit_last",
        "meta_value": "1"
    }
},
{
    "model": "insp.wppostmeta",
    "pk": 168,
    "fields": {
        "post_id": 276,
        "meta_key": "_edit_lock",
        "meta_value": "1390863774:1"
    }
},
{
    "model": "insp.wppostmeta",
    "pk": 169,
    "fields": {
        "post_id": 278,
        "meta_key": "_wp_attached_file",
        "meta_value": "2014/01/rubix1.jpg"
    }
},
{
    "model": "insp.wppostmeta",
    "pk": 170,
    "fields": {
        "post_id": 278,
        "meta_key": "_wp_attachment_metadata",
        "meta_value": "a:5:{s:5:\"width\";i:1936;s:6:\"height\";i:2592;s:4:\"file\";s:18:\"2014/01/rubix1.jpg\";s:5:\"sizes\";a:4:{s:9:\"thumbnail\";a:4:{s:4:\"file\";s:18:\"rubix1-150x150.jpg\";s:5:\"width\";i:150;s:6:\"height\";i:150;s:9:\"mime-type\";s:10:\"image/jpeg\";}s:6:\"medium\";a:4:{s:4:\"file\";s:18:\"rubix1-224x300.jpg\";s:5:\"width\";i:224;s:6:\"height\";i:300;s:9:\"mime-type\";s:10:\"image/jpeg\";}s:5:\"large\";a:4:{s:4:\"file\";s:19:\"rubix1-764x1024.jpg\";s:5:\"width\";i:764;s:6:\"height\";i:1024;s:9:\"mime-type\";s:10:\"image/jpeg\";}s:14:\"post-thumbnail\";a:4:{s:4:\"file\";s:18:\"rubix1-940x198.jpg\";s:5:\"width\";i:940;s:6:\"height\";i:198;s:9:\"mime-type\";s:10:\"image/jpeg\";}}s:10:\"image_meta\";a:10:{s:8:\"aperture\";d:2.79999999999999982236431605997495353221893310546875;s:6:\"credit\";s:0:\"\";s:6:\"camera\";s:8:\"iPhone 4\";s:7:\"caption\";s:0:\"\";s:17:\"created_timestamp\";i:1390866708;s:9:\"copyright\";s:0:\"\";s:12:\"focal_length\";s:4:\"3.85\";s:3:\"iso\";s:3:\"500\";s:13:\"shutter_speed\";s:17:\"0.066666666666667\";s:5:\"title\";s:0:\"\";}}"
    }
},
{
    "model": "insp.wppostmeta",
    "pk": 171,
    "fields": {
        "post_id": 279,
        "meta_key": "_wp_attached_file",
        "meta_value": "2014/01/rubix2.jpg"
    }
},
{
    "model": "insp.wppostmeta",
    "pk": 172,
    "fields": {
        "post_id": 279,
        "meta_key": "_wp_attachment_metadata",
        "meta_value": "a:5:{s:5:\"width\";i:1936;s:6:\"height\";i:2592;s:4:\"file\";s:18:\"2014/01/rubix2.jpg\";s:5:\"sizes\";a:4:{s:9:\"thumbnail\";a:4:{s:4:\"file\";s:18:\"rubix2-150x150.jpg\";s:5:\"width\";i:150;s:6:\"height\";i:150;s:9:\"mime-type\";s:10:\"image/jpeg\";}s:6:\"medium\";a:4:{s:4:\"file\";s:18:\"rubix2-224x300.jpg\";s:5:\"width\";i:224;s:6:\"height\";i:300;s:9:\"mime-type\";s:10:\"image/jpeg\";}s:5:\"large\";a:4:{s:4:\"file\";s:19:\"rubix2-764x1024.jpg\";s:5:\"width\";i:764;s:6:\"height\";i:1024;s:9:\"mime-type\";s:10:\"image/jpeg\";}s:14:\"post-thumbnail\";a:4:{s:4:\"file\";s:18:\"rubix2-940x198.jpg\";s:5:\"width\";i:940;s:6:\"height\";i:198;s:9:\"mime-type\";s:10:\"image/jpeg\";}}s:10:\"image_meta\";a:10:{s:8:\"aperture\";d:2.79999999999999982236431605997495353221893310546875;s:6:\"credit\";s:0:\"\";s:6:\"camera\";s:8:\"iPhone 4\";s:7:\"caption\";s:0:\"\";s:17:\"created_timestamp\";i:1390866641;s:9:\"copyright\";s:0:\"\";s:12:\"focal_length\";s:4:\"3.85\";s:3:\"iso\";s:3:\"500\";s:13:\"shutter_speed\";s:17:\"0.066666666666667\";s:5:\"title\";s:0:\"\";}}"
    }
},
{
    "model": "insp.wppostmeta",
    "pk": 173,
    "fields": {
        "post_id": 277,
        "meta_key": "_edit_last",
        "meta_value": "1"
    }
},
{
    "model": "insp.wppostmeta",
    "pk": 174,
    "fields": {
        "post_id": 277,
        "meta_key": "_edit_lock",
        "meta_value": "1390911301:1"
    }
},
{
    "model": "insp.wppostmeta",
    "pk": 179,
    "fields": {
        "post_id": 284,
        "meta_key": "_edit_last",
        "meta_value": "1"
    }
},
{
    "model": "insp.wppostmeta",
    "pk": 180,
    "fields": {
        "post_id": 284,
        "meta_key": "_edit_lock",
        "meta_value": "1392337702:1"
    }
},
{
    "model": "insp.wppostmeta",
    "pk": 183,
    "fields": {
        "post_id": 286,
        "meta_key": "_edit_last",
        "meta_value": "1"
    }
},
{
    "model": "insp.wppostmeta",
    "pk": 184,
    "fields": {
        "post_id": 286,
        "meta_key": "_edit_lock",
        "meta_value": "1392926126:1"
    }
},
{
    "model": "insp.wppostmeta",
    "pk": 189,
    "fields": {
        "post_id": 291,
        "meta_key": "_edit_last",
        "meta_value": "1"
    }
},
{
    "model": "insp.wppostmeta",
    "pk": 190,
    "fields": {
        "post_id": 291,
        "meta_key": "_edit_lock",
        "meta_value": "1393340302:1"
    }
},
{
    "model": "insp.wppostmeta",
    "pk": 193,
    "fields": {
        "post_id": 293,
        "meta_key": "_edit_last",
        "meta_value": "1"
    }
},
{
    "model": "insp.wppostmeta",
    "pk": 194,
    "fields": {
        "post_id": 293,
        "meta_key": "_edit_lock",
        "meta_value": "1393877878:1"
    }
},
{
    "model": "insp.wppostmeta",
    "pk": 197,
    "fields": {
        "post_id": 296,
        "meta_key": "_edit_last",
        "meta_value": "1"
    }
},
{
    "model": "insp.wppostmeta",
    "pk": 198,
    "fields": {
        "post_id": 296,
        "meta_key": "_edit_lock",
        "meta_value": "1395597633:1"
    }
},
{
    "model": "insp.wppostmeta",
    "pk": 201,
    "fields": {
        "post_id": 299,
        "meta_key": "_edit_last",
        "meta_value": "1"
    }
},
{
    "model": "insp.wppostmeta",
    "pk": 202,
    "fields": {
        "post_id": 299,
        "meta_key": "_edit_lock",
        "meta_value": "1396986515:1"
    }
},
{
    "model": "insp.wppostmeta",
    "pk": 205,
    "fields": {
        "post_id": 304,
        "meta_key": "_wp_attached_file",
        "meta_value": "2014/09/kuklous.jpg"
    }
},
{
    "model": "insp.wppostmeta",
    "pk": 206,
    "fields": {
        "post_id": 304,
        "meta_key": "_wp_attachment_metadata",
        "meta_value": "a:5:{s:5:\"width\";i:800;s:6:\"height\";i:800;s:4:\"file\";s:19:\"2014/09/kuklous.jpg\";s:5:\"sizes\";a:3:{s:9:\"thumbnail\";a:4:{s:4:\"file\";s:19:\"kuklous-150x150.jpg\";s:5:\"width\";i:150;s:6:\"height\";i:150;s:9:\"mime-type\";s:10:\"image/jpeg\";}s:6:\"medium\";a:4:{s:4:\"file\";s:19:\"kuklous-300x300.jpg\";s:5:\"width\";i:300;s:6:\"height\";i:300;s:9:\"mime-type\";s:10:\"image/jpeg\";}s:14:\"post-thumbnail\";a:4:{s:4:\"file\";s:19:\"kuklous-800x198.jpg\";s:5:\"width\";i:800;s:6:\"height\";i:198;s:9:\"mime-type\";s:10:\"image/jpeg\";}}s:10:\"image_meta\";a:10:{s:8:\"aperture\";i:0;s:6:\"credit\";s:0:\"\";s:6:\"camera\";s:0:\"\";s:7:\"caption\";s:0:\"\";s:17:\"created_timestamp\";i:0;s:9:\"copyright\";s:0:\"\";s:12:\"focal_length\";i:0;s:3:\"iso\";i:0;s:13:\"shutter_speed\";i:0;s:5:\"title\";s:0:\"\";}}"
    }
},
{
    "model": "insp.wppostmeta",
    "pk": 207,
    "fields": {
        "post_id": 303,
        "meta_key": "_edit_last",
        "meta_value": "1"
    }
},
{
    "model": "insp.wppostmeta",
    "pk": 208,
    "fields": {
        "post_id": 303,
        "meta_key": "_edit_lock",
        "meta_value": "1410948730:1"
    }
},
{
    "model": "insp.wppostmeta",
    "pk": 211,
    "fields": {
        "post_id": 307,
        "meta_key": "_edit_last",
        "meta_value": "1"
    }
},
{
    "model": "insp.wppostmeta",
    "pk": 212,
    "fields": {
        "post_id": 307,
        "meta_key": "_edit_lock",
        "meta_value": "1412678005:1"
    }
},
{
    "model": "insp.wppostmeta",
    "pk": 213,
    "fields": {
        "post_id": 308,
        "meta_key": "_wp_attached_file",
        "meta_value": "2014/10/eggonopoulos.jpg"
    }
},
{
    "model": "insp.wppostmeta",
    "pk": 214,
    "fields": {
        "post_id": 308,
        "meta_key": "_wp_attachment_metadata",
        "meta_value": "a:5:{s:5:\"width\";i:342;s:6:\"height\";i:400;s:4:\"file\";s:24:\"2014/10/eggonopoulos.jpg\";s:5:\"sizes\";a:3:{s:9:\"thumbnail\";a:4:{s:4:\"file\";s:24:\"eggonopoulos-150x150.jpg\";s:5:\"width\";i:150;s:6:\"height\";i:150;s:9:\"mime-type\";s:10:\"image/jpeg\";}s:6:\"medium\";a:4:{s:4:\"file\";s:24:\"eggonopoulos-256x300.jpg\";s:5:\"width\";i:256;s:6:\"height\";i:300;s:9:\"mime-type\";s:10:\"image/jpeg\";}s:14:\"post-thumbnail\";a:4:{s:4:\"file\";s:24:\"eggonopoulos-342x198.jpg\";s:5:\"width\";i:342;s:6:\"height\";i:198;s:9:\"mime-type\";s:10:\"image/jpeg\";}}s:10:\"image_meta\";a:10:{s:8:\"aperture\";i:0;s:6:\"credit\";s:0:\"\";s:6:\"camera\";s:0:\"\";s:7:\"caption\";s:0:\"\";s:17:\"created_timestamp\";i:0;s:9:\"copyright\";s:0:\"\";s:12:\"focal_length\";i:0;s:3:\"iso\";i:0;s:13:\"shutter_speed\";i:0;s:5:\"title\";s:0:\"\";}}"
    }
},
{
    "model": "insp.wppostmeta",
    "pk": 217,
    "fields": {
        "post_id": 310,
        "meta_key": "_edit_last",
        "meta_value": "1"
    }
},
{
    "model": "insp.wppostmeta",
    "pk": 218,
    "fields": {
        "post_id": 310,
        "meta_key": "_edit_lock",
        "meta_value": "1413124921:1"
    }
},
{
    "model": "insp.wppostmeta",
    "pk": 219,
    "fields": {
        "post_id": 311,
        "meta_key": "_wp_attached_file",
        "meta_value": "2014/10/manga_00_cropped.jpg"
    }
},
{
    "model": "insp.wppostmeta",
    "pk": 220,
    "fields": {
        "post_id": 311,
        "meta_key": "_wp_attachment_metadata",
        "meta_value": "a:5:{s:5:\"width\";i:1071;s:6:\"height\";i:1285;s:4:\"file\";s:28:\"2014/10/manga_00_cropped.jpg\";s:5:\"sizes\";a:4:{s:9:\"thumbnail\";a:4:{s:4:\"file\";s:28:\"manga_00_cropped-150x150.jpg\";s:5:\"width\";i:150;s:6:\"height\";i:150;s:9:\"mime-type\";s:10:\"image/jpeg\";}s:6:\"medium\";a:4:{s:4:\"file\";s:28:\"manga_00_cropped-250x300.jpg\";s:5:\"width\";i:250;s:6:\"height\";i:300;s:9:\"mime-type\";s:10:\"image/jpeg\";}s:5:\"large\";a:4:{s:4:\"file\";s:29:\"manga_00_cropped-853x1024.jpg\";s:5:\"width\";i:853;s:6:\"height\";i:1024;s:9:\"mime-type\";s:10:\"image/jpeg\";}s:14:\"post-thumbnail\";a:4:{s:4:\"file\";s:28:\"manga_00_cropped-940x198.jpg\";s:5:\"width\";i:940;s:6:\"height\";i:198;s:9:\"mime-type\";s:10:\"image/jpeg\";}}s:10:\"image_meta\";a:10:{s:8:\"aperture\";i:0;s:6:\"credit\";s:0:\"\";s:6:\"camera\";s:0:\"\";s:7:\"caption\";s:0:\"\";s:17:\"created_timestamp\";i:0;s:9:\"copyright\";s:0:\"\";s:12:\"focal_length\";i:0;s:3:\"iso\";i:0;s:13:\"shutter_speed\";i:0;s:5:\"title\";s:0:\"\";}}"
    }
},
{
    "model": "insp.wppostmeta",
    "pk": 223,
    "fields": {
        "post_id": 314,
        "meta_key": "_edit_last",
        "meta_value": "1"
    }
},
{
    "model": "insp.wppostmeta",
    "pk": 224,
    "fields": {
        "post_id": 314,
        "meta_key": "_edit_lock",
        "meta_value": "1413130782:1"
    }
},
{
    "model": "insp.wppostmeta",
    "pk": 225,
    "fields": {
        "post_id": 315,
        "meta_key": "_wp_attached_file",
        "meta_value": "2014/10/manga_01_cropped.jpg"
    }
},
{
    "model": "insp.wppostmeta",
    "pk": 226,
    "fields": {
        "post_id": 315,
        "meta_key": "_wp_attachment_metadata",
        "meta_value": "a:5:{s:5:\"width\";i:965;s:6:\"height\";i:978;s:4:\"file\";s:28:\"2014/10/manga_01_cropped.jpg\";s:5:\"sizes\";a:3:{s:9:\"thumbnail\";a:4:{s:4:\"file\";s:28:\"manga_01_cropped-150x150.jpg\";s:5:\"width\";i:150;s:6:\"height\";i:150;s:9:\"mime-type\";s:10:\"image/jpeg\";}s:6:\"medium\";a:4:{s:4:\"file\";s:28:\"manga_01_cropped-296x300.jpg\";s:5:\"width\";i:296;s:6:\"height\";i:300;s:9:\"mime-type\";s:10:\"image/jpeg\";}s:14:\"post-thumbnail\";a:4:{s:4:\"file\";s:28:\"manga_01_cropped-940x198.jpg\";s:5:\"width\";i:940;s:6:\"height\";i:198;s:9:\"mime-type\";s:10:\"image/jpeg\";}}s:10:\"image_meta\";a:10:{s:8:\"aperture\";i:0;s:6:\"credit\";s:0:\"\";s:6:\"camera\";s:0:\"\";s:7:\"caption\";s:0:\"\";s:17:\"created_timestamp\";i:0;s:9:\"copyright\";s:0:\"\";s:12:\"focal_length\";i:0;s:3:\"iso\";i:0;s:13:\"shutter_speed\";i:0;s:5:\"title\";s:0:\"\";}}"
    }
},
{
    "model": "insp.wppostmeta",
    "pk": 229,
    "fields": {
        "post_id": 318,
        "meta_key": "_edit_last",
        "meta_value": "1"
    }
},
{
    "model": "insp.wppostmeta",
    "pk": 230,
    "fields": {
        "post_id": 318,
        "meta_key": "_edit_lock",
        "meta_value": "1413140501:1"
    }
},
{
    "model": "insp.wppostmeta",
    "pk": 231,
    "fields": {
        "post_id": 319,
        "meta_key": "_wp_attached_file",
        "meta_value": "2014/10/manga_03_cropped.jpg"
    }
},
{
    "model": "insp.wppostmeta",
    "pk": 232,
    "fields": {
        "post_id": 319,
        "meta_key": "_wp_attachment_metadata",
        "meta_value": "a:5:{s:5:\"width\";i:877;s:6:\"height\";i:807;s:4:\"file\";s:28:\"2014/10/manga_03_cropped.jpg\";s:5:\"sizes\";a:3:{s:9:\"thumbnail\";a:4:{s:4:\"file\";s:28:\"manga_03_cropped-150x150.jpg\";s:5:\"width\";i:150;s:6:\"height\";i:150;s:9:\"mime-type\";s:10:\"image/jpeg\";}s:6:\"medium\";a:4:{s:4:\"file\";s:28:\"manga_03_cropped-300x276.jpg\";s:5:\"width\";i:300;s:6:\"height\";i:276;s:9:\"mime-type\";s:10:\"image/jpeg\";}s:14:\"post-thumbnail\";a:4:{s:4:\"file\";s:28:\"manga_03_cropped-877x198.jpg\";s:5:\"width\";i:877;s:6:\"height\";i:198;s:9:\"mime-type\";s:10:\"image/jpeg\";}}s:10:\"image_meta\";a:10:{s:8:\"aperture\";i:0;s:6:\"credit\";s:0:\"\";s:6:\"camera\";s:0:\"\";s:7:\"caption\";s:0:\"\";s:17:\"created_timestamp\";i:0;s:9:\"copyright\";s:0:\"\";s:12:\"focal_length\";i:0;s:3:\"iso\";i:0;s:13:\"shutter_speed\";i:0;s:5:\"title\";s:0:\"\";}}"
    }
},
{
    "model": "insp.wppostmeta",
    "pk": 235,
    "fields": {
        "post_id": 321,
        "meta_key": "_edit_last",
        "meta_value": "1"
    }
},
{
    "model": "insp.wppostmeta",
    "pk": 236,
    "fields": {
        "post_id": 321,
        "meta_key": "_edit_lock",
        "meta_value": "1413230047:1"
    }
},
{
    "model": "insp.wppostmeta",
    "pk": 237,
    "fields": {
        "post_id": 322,
        "meta_key": "_wp_attached_file",
        "meta_value": "2014/10/manga_04_res_crop.jpg"
    }
},
{
    "model": "insp.wppostmeta",
    "pk": 238,
    "fields": {
        "post_id": 322,
        "meta_key": "_wp_attachment_metadata",
        "meta_value": "a:5:{s:5:\"width\";i:789;s:6:\"height\";i:1037;s:4:\"file\";s:29:\"2014/10/manga_04_res_crop.jpg\";s:5:\"sizes\";a:4:{s:9:\"thumbnail\";a:4:{s:4:\"file\";s:29:\"manga_04_res_crop-150x150.jpg\";s:5:\"width\";i:150;s:6:\"height\";i:150;s:9:\"mime-type\";s:10:\"image/jpeg\";}s:6:\"medium\";a:4:{s:4:\"file\";s:29:\"manga_04_res_crop-228x300.jpg\";s:5:\"width\";i:228;s:6:\"height\";i:300;s:9:\"mime-type\";s:10:\"image/jpeg\";}s:5:\"large\";a:4:{s:4:\"file\";s:30:\"manga_04_res_crop-779x1024.jpg\";s:5:\"width\";i:779;s:6:\"height\";i:1024;s:9:\"mime-type\";s:10:\"image/jpeg\";}s:14:\"post-thumbnail\";a:4:{s:4:\"file\";s:29:\"manga_04_res_crop-789x198.jpg\";s:5:\"width\";i:789;s:6:\"height\";i:198;s:9:\"mime-type\";s:10:\"image/jpeg\";}}s:10:\"image_meta\";a:10:{s:8:\"aperture\";i:0;s:6:\"credit\";s:0:\"\";s:6:\"camera\";s:0:\"\";s:7:\"caption\";s:0:\"\";s:17:\"created_timestamp\";i:0;s:9:\"copyright\";s:0:\"\";s:12:\"focal_length\";i:0;s:3:\"iso\";i:0;s:13:\"shutter_speed\";i:0;s:5:\"title\";s:0:\"\";}}"
    }
},
{
    "model": "insp.wppostmeta",
    "pk": 241,
    "fields": {
        "post_id": 238,
        "meta_key": "_edit_lock",
        "meta_value": "1413819143:1"
    }
},
{
    "model": "insp.wppostmeta",
    "pk": 242,
    "fields": {
        "post_id": 326,
        "meta_key": "_edit_last",
        "meta_value": "1"
    }
},
{
    "model": "insp.wppostmeta",
    "pk": 243,
    "fields": {
        "post_id": 326,
        "meta_key": "_edit_lock",
        "meta_value": "1415920417:1"
    }
},
{
    "model": "insp.wppostmeta",
    "pk": 252,
    "fields": {
        "post_id": 331,
        "meta_key": "_edit_last",
        "meta_value": "1"
    }
},
{
    "model": "insp.wppostmeta",
    "pk": 253,
    "fields": {
        "post_id": 331,
        "meta_key": "_edit_lock",
        "meta_value": "1414146755:1"
    }
},
{
    "model": "insp.wppostmeta",
    "pk": 254,
    "fields": {
        "post_id": 332,
        "meta_key": "_wp_attached_file",
        "meta_value": "2014/10/utube_comments_1.png"
    }
},
{
    "model": "insp.wppostmeta",
    "pk": 255,
    "fields": {
        "post_id": 332,
        "meta_key": "_wp_attachment_metadata",
        "meta_value": "a:5:{s:5:\"width\";i:937;s:6:\"height\";i:436;s:4:\"file\";s:28:\"2014/10/utube_comments_1.png\";s:5:\"sizes\";a:3:{s:9:\"thumbnail\";a:4:{s:4:\"file\";s:28:\"utube_comments_1-150x150.png\";s:5:\"width\";i:150;s:6:\"height\";i:150;s:9:\"mime-type\";s:9:\"image/png\";}s:6:\"medium\";a:4:{s:4:\"file\";s:28:\"utube_comments_1-300x139.png\";s:5:\"width\";i:300;s:6:\"height\";i:139;s:9:\"mime-type\";s:9:\"image/png\";}s:14:\"post-thumbnail\";a:4:{s:4:\"file\";s:28:\"utube_comments_1-937x198.png\";s:5:\"width\";i:937;s:6:\"height\";i:198;s:9:\"mime-type\";s:9:\"image/png\";}}s:10:\"image_meta\";a:10:{s:8:\"aperture\";i:0;s:6:\"credit\";s:0:\"\";s:6:\"camera\";s:0:\"\";s:7:\"caption\";s:0:\"\";s:17:\"created_timestamp\";i:0;s:9:\"copyright\";s:0:\"\";s:12:\"focal_length\";i:0;s:3:\"iso\";i:0;s:13:\"shutter_speed\";i:0;s:5:\"title\";s:0:\"\";}}"
    }
},
{
    "model": "insp.wppostmeta",
    "pk": 260,
    "fields": {
        "post_id": 122,
        "meta_key": "_edit_lock",
        "meta_value": "1414146398:1"
    }
},
{
    "model": "insp.wppostmeta",
    "pk": 263,
    "fields": {
        "post_id": 211,
        "meta_key": "_edit_lock",
        "meta_value": "1414146760:1"
    }
},
{
    "model": "insp.wppostmeta",
    "pk": 272,
    "fields": {
        "post_id": 342,
        "meta_key": "_edit_last",
        "meta_value": "1"
    }
},
{
    "model": "insp.wppostmeta",
    "pk": 273,
    "fields": {
        "post_id": 342,
        "meta_key": "_edit_lock",
        "meta_value": "1414575460:1"
    }
},
{
    "model": "insp.wppostmeta",
    "pk": 274,
    "fields": {
        "post_id": 343,
        "meta_key": "_wp_attached_file",
        "meta_value": "2014/10/photo-1.jpg"
    }
},
{
    "model": "insp.wppostmeta",
    "pk": 275,
    "fields": {
        "post_id": 343,
        "meta_key": "_wp_attachment_metadata",
        "meta_value": "a:5:{s:5:\"width\";i:1296;s:6:\"height\";i:968;s:4:\"file\";s:19:\"2014/10/photo-1.jpg\";s:5:\"sizes\";a:4:{s:9:\"thumbnail\";a:4:{s:4:\"file\";s:19:\"photo-1-150x150.jpg\";s:5:\"width\";i:150;s:6:\"height\";i:150;s:9:\"mime-type\";s:10:\"image/jpeg\";}s:6:\"medium\";a:4:{s:4:\"file\";s:19:\"photo-1-300x224.jpg\";s:5:\"width\";i:300;s:6:\"height\";i:224;s:9:\"mime-type\";s:10:\"image/jpeg\";}s:5:\"large\";a:4:{s:4:\"file\";s:20:\"photo-1-1024x764.jpg\";s:5:\"width\";i:1024;s:6:\"height\";i:764;s:9:\"mime-type\";s:10:\"image/jpeg\";}s:14:\"post-thumbnail\";a:4:{s:4:\"file\";s:19:\"photo-1-940x198.jpg\";s:5:\"width\";i:940;s:6:\"height\";i:198;s:9:\"mime-type\";s:10:\"image/jpeg\";}}s:10:\"image_meta\";a:10:{s:8:\"aperture\";d:2.7999999999999998;s:6:\"credit\";s:0:\"\";s:6:\"camera\";s:8:\"iPhone 4\";s:7:\"caption\";s:0:\"\";s:17:\"created_timestamp\";i:1414246984;s:9:\"copyright\";s:0:\"\";s:12:\"focal_length\";s:4:\"3.85\";s:3:\"iso\";s:2:\"80\";s:13:\"shutter_speed\";s:18:\"0.0024213075060533\";s:5:\"title\";s:0:\"\";}}"
    }
},
{
    "model": "insp.wppostmeta",
    "pk": 276,
    "fields": {
        "post_id": 344,
        "meta_key": "_wp_attached_file",
        "meta_value": "2014/10/photo-2.jpg"
    }
},
{
    "model": "insp.wppostmeta",
    "pk": 277,
    "fields": {
        "post_id": 344,
        "meta_key": "_wp_attachment_metadata",
        "meta_value": "a:5:{s:5:\"width\";i:1296;s:6:\"height\";i:968;s:4:\"file\";s:19:\"2014/10/photo-2.jpg\";s:5:\"sizes\";a:4:{s:9:\"thumbnail\";a:4:{s:4:\"file\";s:19:\"photo-2-150x150.jpg\";s:5:\"width\";i:150;s:6:\"height\";i:150;s:9:\"mime-type\";s:10:\"image/jpeg\";}s:6:\"medium\";a:4:{s:4:\"file\";s:19:\"photo-2-300x224.jpg\";s:5:\"width\";i:300;s:6:\"height\";i:224;s:9:\"mime-type\";s:10:\"image/jpeg\";}s:5:\"large\";a:4:{s:4:\"file\";s:20:\"photo-2-1024x764.jpg\";s:5:\"width\";i:1024;s:6:\"height\";i:764;s:9:\"mime-type\";s:10:\"image/jpeg\";}s:14:\"post-thumbnail\";a:4:{s:4:\"file\";s:19:\"photo-2-940x198.jpg\";s:5:\"width\";i:940;s:6:\"height\";i:198;s:9:\"mime-type\";s:10:\"image/jpeg\";}}s:10:\"image_meta\";a:10:{s:8:\"aperture\";d:2.7999999999999998;s:6:\"credit\";s:0:\"\";s:6:\"camera\";s:8:\"iPhone 4\";s:7:\"caption\";s:0:\"\";s:17:\"created_timestamp\";i:1414249012;s:9:\"copyright\";s:0:\"\";s:12:\"focal_length\";s:4:\"3.85\";s:3:\"iso\";s:2:\"80\";s:13:\"shutter_speed\";s:18:\"0.0019569471624266\";s:5:\"title\";s:0:\"\";}}"
    }
},
{
    "model": "insp.wppostmeta",
    "pk": 280,
    "fields": {
        "post_id": 346,
        "meta_key": "_edit_last",
        "meta_value": "1"
    }
},
{
    "model": "insp.wppostmeta",
    "pk": 281,
    "fields": {
        "post_id": 346,
        "meta_key": "_edit_lock",
        "meta_value": "1414663427:1"
    }
},
{
    "model": "insp.wppostmeta",
    "pk": 284,
    "fields": {
        "post_id": 349,
        "meta_key": "_edit_last",
        "meta_value": "1"
    }
},
{
    "model": "insp.wppostmeta",
    "pk": 285,
    "fields": {
        "post_id": 349,
        "meta_key": "_edit_lock",
        "meta_value": "1414686142:1"
    }
},
{
    "model": "insp.wppostmeta",
    "pk": 288,
    "fields": {
        "post_id": 352,
        "meta_key": "_edit_last",
        "meta_value": "1"
    }
},
{
    "model": "insp.wppostmeta",
    "pk": 289,
    "fields": {
        "post_id": 352,
        "meta_key": "_edit_lock",
        "meta_value": "1414858251:1"
    }
},
{
    "model": "insp.wppostmeta",
    "pk": 290,
    "fields": {
        "post_id": 353,
        "meta_key": "_wp_attached_file",
        "meta_value": "2014/11/random_manga_face.jpg"
    }
},
{
    "model": "insp.wppostmeta",
    "pk": 291,
    "fields": {
        "post_id": 353,
        "meta_key": "_wp_attachment_metadata",
        "meta_value": "a:5:{s:5:\"width\";i:720;s:6:\"height\";i:486;s:4:\"file\";s:29:\"2014/11/random_manga_face.jpg\";s:5:\"sizes\";a:3:{s:9:\"thumbnail\";a:4:{s:4:\"file\";s:29:\"random_manga_face-150x150.jpg\";s:5:\"width\";i:150;s:6:\"height\";i:150;s:9:\"mime-type\";s:10:\"image/jpeg\";}s:6:\"medium\";a:4:{s:4:\"file\";s:29:\"random_manga_face-300x202.jpg\";s:5:\"width\";i:300;s:6:\"height\";i:202;s:9:\"mime-type\";s:10:\"image/jpeg\";}s:14:\"post-thumbnail\";a:4:{s:4:\"file\";s:29:\"random_manga_face-720x198.jpg\";s:5:\"width\";i:720;s:6:\"height\";i:198;s:9:\"mime-type\";s:10:\"image/jpeg\";}}s:10:\"image_meta\";a:10:{s:8:\"aperture\";i:0;s:6:\"credit\";s:0:\"\";s:6:\"camera\";s:0:\"\";s:7:\"caption\";s:0:\"\";s:17:\"created_timestamp\";i:0;s:9:\"copyright\";s:0:\"\";s:12:\"focal_length\";i:0;s:3:\"iso\";i:0;s:13:\"shutter_speed\";i:0;s:5:\"title\";s:0:\"\";}}"
    }
},
{
    "model": "insp.wppostmeta",
    "pk": 296,
    "fields": {
        "post_id": 358,
        "meta_key": "_wp_attached_file",
        "meta_value": "2014/11/finn_res.jpg"
    }
},
{
    "model": "insp.wppostmeta",
    "pk": 297,
    "fields": {
        "post_id": 358,
        "meta_key": "_wp_attachment_metadata",
        "meta_value": "a:5:{s:5:\"width\";i:896;s:6:\"height\";i:1200;s:4:\"file\";s:20:\"2014/11/finn_res.jpg\";s:5:\"sizes\";a:4:{s:9:\"thumbnail\";a:4:{s:4:\"file\";s:20:\"finn_res-150x150.jpg\";s:5:\"width\";i:150;s:6:\"height\";i:150;s:9:\"mime-type\";s:10:\"image/jpeg\";}s:6:\"medium\";a:4:{s:4:\"file\";s:20:\"finn_res-224x300.jpg\";s:5:\"width\";i:224;s:6:\"height\";i:300;s:9:\"mime-type\";s:10:\"image/jpeg\";}s:5:\"large\";a:4:{s:4:\"file\";s:21:\"finn_res-764x1024.jpg\";s:5:\"width\";i:764;s:6:\"height\";i:1024;s:9:\"mime-type\";s:10:\"image/jpeg\";}s:14:\"post-thumbnail\";a:4:{s:4:\"file\";s:20:\"finn_res-896x198.jpg\";s:5:\"width\";i:896;s:6:\"height\";i:198;s:9:\"mime-type\";s:10:\"image/jpeg\";}}s:10:\"image_meta\";a:10:{s:8:\"aperture\";i:0;s:6:\"credit\";s:0:\"\";s:6:\"camera\";s:0:\"\";s:7:\"caption\";s:0:\"\";s:17:\"created_timestamp\";i:0;s:9:\"copyright\";s:0:\"\";s:12:\"focal_length\";i:0;s:3:\"iso\";i:0;s:13:\"shutter_speed\";i:0;s:5:\"title\";s:0:\"\";}}"
    }
},
{
    "model": "insp.wppostmeta",
    "pk": 298,
    "fields": {
        "post_id": 356,
        "meta_key": "_edit_last",
        "meta_value": "1"
    }
},
{
    "model": "insp.wppostmeta",
    "pk": 299,
    "fields": {
        "post_id": 356,
        "meta_key": "_edit_lock",
        "meta_value": "1415352435:1"
    }
},
{
    "model": "insp.wppostmeta",
    "pk": 304,
    "fields": {
        "post_id": 363,
        "meta_key": "_edit_last",
        "meta_value": "1"
    }
},
{
    "model": "insp.wppostmeta",
    "pk": 305,
    "fields": {
        "post_id": 363,
        "meta_key": "_edit_lock",
        "meta_value": "1415920467:1"
    }
},
{
    "model": "insp.wppostmeta",
    "pk": 308,
    "fields": {
        "post_id": 370,
        "meta_key": "_edit_last",
        "meta_value": "1"
    }
},
{
    "model": "insp.wppostmeta",
    "pk": 309,
    "fields": {
        "post_id": 370,
        "meta_key": "_edit_lock",
        "meta_value": "1416054445:1"
    }
},
{
    "model": "insp.wppostmeta",
    "pk": 310,
    "fields": {
        "post_id": 371,
        "meta_key": "_wp_attached_file",
        "meta_value": "2014/11/drink_some_2.jpg"
    }
},
{
    "model": "insp.wppostmeta",
    "pk": 311,
    "fields": {
        "post_id": 371,
        "meta_key": "_wp_attachment_metadata",
        "meta_value": "a:5:{s:5:\"width\";i:640;s:6:\"height\";i:960;s:4:\"file\";s:24:\"2014/11/drink_some_2.jpg\";s:5:\"sizes\";a:3:{s:9:\"thumbnail\";a:4:{s:4:\"file\";s:24:\"drink_some_2-150x150.jpg\";s:5:\"width\";i:150;s:6:\"height\";i:150;s:9:\"mime-type\";s:10:\"image/jpeg\";}s:6:\"medium\";a:4:{s:4:\"file\";s:24:\"drink_some_2-200x300.jpg\";s:5:\"width\";i:200;s:6:\"height\";i:300;s:9:\"mime-type\";s:10:\"image/jpeg\";}s:14:\"post-thumbnail\";a:4:{s:4:\"file\";s:24:\"drink_some_2-640x198.jpg\";s:5:\"width\";i:640;s:6:\"height\";i:198;s:9:\"mime-type\";s:10:\"image/jpeg\";}}s:10:\"image_meta\";a:10:{s:8:\"aperture\";i:0;s:6:\"credit\";s:0:\"\";s:6:\"camera\";s:0:\"\";s:7:\"caption\";s:0:\"\";s:17:\"created_timestamp\";i:0;s:9:\"copyright\";s:0:\"\";s:12:\"focal_length\";i:0;s:3:\"iso\";i:0;s:13:\"shutter_speed\";i:0;s:5:\"title\";s:0:\"\";}}"
    }
},
{
    "model": "insp.wppostmeta",
    "pk": 316,
    "fields": {
        "post_id": 375,
        "meta_key": "_edit_last",
        "meta_value": "1"
    }
},
{
    "model": "insp.wppostmeta",
    "pk": 317,
    "fields": {
        "post_id": 375,
        "meta_key": "_edit_lock",
        "meta_value": "1416817982:1"
    }
},
{
    "model": "insp.wppostmeta",
    "pk": 318,
    "fields": {
        "post_id": 376,
        "meta_key": "_wp_attached_file",
        "meta_value": "2014/11/ytc.png"
    }
},
{
    "model": "insp.wppostmeta",
    "pk": 319,
    "fields": {
        "post_id": 376,
        "meta_key": "_wp_attachment_metadata",
        "meta_value": "a:5:{s:5:\"width\";i:603;s:6:\"height\";i:326;s:4:\"file\";s:15:\"2014/11/ytc.png\";s:5:\"sizes\";a:3:{s:9:\"thumbnail\";a:4:{s:4:\"file\";s:15:\"ytc-150x150.png\";s:5:\"width\";i:150;s:6:\"height\";i:150;s:9:\"mime-type\";s:9:\"image/png\";}s:6:\"medium\";a:4:{s:4:\"file\";s:15:\"ytc-300x162.png\";s:5:\"width\";i:300;s:6:\"height\";i:162;s:9:\"mime-type\";s:9:\"image/png\";}s:14:\"post-thumbnail\";a:4:{s:4:\"file\";s:15:\"ytc-603x198.png\";s:5:\"width\";i:603;s:6:\"height\";i:198;s:9:\"mime-type\";s:9:\"image/png\";}}s:10:\"image_meta\";a:10:{s:8:\"aperture\";i:0;s:6:\"credit\";s:0:\"\";s:6:\"camera\";s:0:\"\";s:7:\"caption\";s:0:\"\";s:17:\"created_timestamp\";i:0;s:9:\"copyright\";s:0:\"\";s:12:\"focal_length\";i:0;s:3:\"iso\";i:0;s:13:\"shutter_speed\";i:0;s:5:\"title\";s:0:\"\";}}"
    }
},
{
    "model": "insp.wppostmeta",
    "pk": 322,
    "fields": {
        "post_id": 380,
        "meta_key": "_edit_last",
        "meta_value": "1"
    }
},
{
    "model": "insp.wppostmeta",
    "pk": 323,
    "fields": {
        "post_id": 380,
        "meta_key": "_edit_lock",
        "meta_value": "1417771651:1"
    }
},
{
    "model": "insp.wppostmeta",
    "pk": 326,
    "fields": {
        "post_id": 388,
        "meta_key": "_edit_last",
        "meta_value": "1"
    }
},
{
    "model": "insp.wppostmeta",
    "pk": 327,
    "fields": {
        "post_id": 388,
        "meta_key": "_edit_lock",
        "meta_value": "1427523679:1"
    }
},
{
    "model": "insp.wppostmeta",
    "pk": 330,
    "fields": {
        "post_id": 391,
        "meta_key": "_edit_last",
        "meta_value": "1"
    }
},
{
    "model": "insp.wppostmeta",
    "pk": 331,
    "fields": {
        "post_id": 391,
        "meta_key": "_edit_lock",
        "meta_value": "1432217606:1"
    }
},
{
    "model": "insp.wppostmeta",
    "pk": 334,
    "fields": {
        "post_id": 394,
        "meta_key": "_edit_last",
        "meta_value": "1"
    }
},
{
    "model": "insp.wppostmeta",
    "pk": 335,
    "fields": {
        "post_id": 394,
        "meta_key": "_edit_lock",
        "meta_value": "1436209340:1"
    }
},
{
    "model": "insp.wppostmeta",
    "pk": 336,
    "fields": {
        "post_id": 395,
        "meta_key": "_wp_attached_file",
        "meta_value": "2015/07/lizard4.jpg"
    }
},
{
    "model": "insp.wppostmeta",
    "pk": 337,
    "fields": {
        "post_id": 395,
        "meta_key": "_wp_attachment_metadata",
        "meta_value": "a:5:{s:5:\"width\";i:979;s:6:\"height\";i:1306;s:4:\"file\";s:19:\"2015/07/lizard4.jpg\";s:5:\"sizes\";a:4:{s:9:\"thumbnail\";a:4:{s:4:\"file\";s:19:\"lizard4-150x150.jpg\";s:5:\"width\";i:150;s:6:\"height\";i:150;s:9:\"mime-type\";s:10:\"image/jpeg\";}s:6:\"medium\";a:4:{s:4:\"file\";s:19:\"lizard4-224x300.jpg\";s:5:\"width\";i:224;s:6:\"height\";i:300;s:9:\"mime-type\";s:10:\"image/jpeg\";}s:5:\"large\";a:4:{s:4:\"file\";s:20:\"lizard4-767x1024.jpg\";s:5:\"width\";i:767;s:6:\"height\";i:1024;s:9:\"mime-type\";s:10:\"image/jpeg\";}s:14:\"post-thumbnail\";a:4:{s:4:\"file\";s:19:\"lizard4-940x198.jpg\";s:5:\"width\";i:940;s:6:\"height\";i:198;s:9:\"mime-type\";s:10:\"image/jpeg\";}}s:10:\"image_meta\";a:10:{s:8:\"aperture\";d:2.2000000000000002;s:6:\"credit\";s:0:\"\";s:6:\"camera\";s:9:\"iPhone 5s\";s:7:\"caption\";s:0:\"\";s:17:\"created_timestamp\";i:1436192347;s:9:\"copyright\";s:0:\"\";s:12:\"focal_length\";s:4:\"4.15\";s:3:\"iso\";s:2:\"40\";s:13:\"shutter_speed\";s:18:\"0.0083333333333333\";s:5:\"title\";s:0:\"\";}}"
    }
}
]
